{
"meta":{"test_sets":[],"test_metrics":[],"learn_metrics":[{"best_value":"Min","name":"Logloss"}],"launch_mode":"Train","parameters":"","iteration_count":1000,"learn_sets":["learn"],"name":"experiment"},
"iterations":[
{"learn":[0.6860210076],"iteration":0,"passed_time":0.0004509373266,"remaining_time":0.4504863892},
{"learn":[0.679367999],"iteration":1,"passed_time":0.0007666726181,"remaining_time":0.3825696365},
{"learn":[0.6722515123],"iteration":2,"passed_time":0.001141196838,"remaining_time":0.3792577491},
{"learn":[0.6659410683],"iteration":3,"passed_time":0.001545011359,"remaining_time":0.3847078285},
{"learn":[0.6593109856],"iteration":4,"passed_time":0.001963158547,"remaining_time":0.3906685508},
{"learn":[0.6526537483],"iteration":5,"passed_time":0.002396013382,"remaining_time":0.3969395504},
{"learn":[0.6465860277],"iteration":6,"passed_time":0.002943196225,"remaining_time":0.4175134074},
{"learn":[0.6404777825],"iteration":7,"passed_time":0.003387717184,"remaining_time":0.4200769309},
{"learn":[0.6341804386],"iteration":8,"passed_time":0.003909942857,"remaining_time":0.4305281523},
{"learn":[0.6285414694],"iteration":9,"passed_time":0.004297383141,"remaining_time":0.425440931},
{"learn":[0.6221238187],"iteration":10,"passed_time":0.0047290297,"remaining_time":0.4251827612},
{"learn":[0.6161140824],"iteration":11,"passed_time":0.00527433763,"remaining_time":0.4342537982},
{"learn":[0.6107412442],"iteration":12,"passed_time":0.005701776051,"remaining_time":0.4328963817},
{"learn":[0.6054957948],"iteration":13,"passed_time":0.006088591365,"remaining_time":0.4288107918},
{"learn":[0.5999454466],"iteration":14,"passed_time":0.006620608248,"remaining_time":0.4347532749},
{"learn":[0.5943099875],"iteration":15,"passed_time":0.006985966228,"remaining_time":0.429636923},
{"learn":[0.5892626863],"iteration":16,"passed_time":0.007411571401,"remaining_time":0.4285632169},
{"learn":[0.5847828346],"iteration":17,"passed_time":0.007752513852,"remaining_time":0.4229427001},
{"learn":[0.5794149477],"iteration":18,"passed_time":0.008173285917,"remaining_time":0.4219996571},
{"learn":[0.5737196018],"iteration":19,"passed_time":0.008537060637,"remaining_time":0.4183159712},
{"learn":[0.5694110743],"iteration":20,"passed_time":0.008888085951,"remaining_time":0.4143541022},
{"learn":[0.5652192435],"iteration":21,"passed_time":0.009301316701,"remaining_time":0.4134858061},
{"learn":[0.561132195],"iteration":22,"passed_time":0.009733463236,"remaining_time":0.4134605905},
{"learn":[0.5568245532],"iteration":23,"passed_time":0.01012398671,"remaining_time":0.4117087929},
{"learn":[0.5523030914],"iteration":24,"passed_time":0.01051559347,"remaining_time":0.4101081452},
{"learn":[0.5487270598],"iteration":25,"passed_time":0.01092619934,"remaining_time":0.4093122368},
{"learn":[0.5446023319],"iteration":26,"passed_time":0.01136959535,"remaining_time":0.4097265288},
{"learn":[0.5403305488],"iteration":27,"passed_time":0.01175945219,"remaining_time":0.4082209832},
{"learn":[0.5367268023],"iteration":28,"passed_time":0.01215493377,"remaining_time":0.4069807133},
{"learn":[0.5333633472],"iteration":29,"passed_time":0.0124239629,"remaining_time":0.4017081338},
{"learn":[0.529667469],"iteration":30,"passed_time":0.01280777835,"remaining_time":0.4003463621},
{"learn":[0.5257255383],"iteration":31,"passed_time":0.01321734261,"remaining_time":0.3998246139},
{"learn":[0.5223202431],"iteration":32,"passed_time":0.01373702673,"remaining_time":0.4025365106},
{"learn":[0.5187438038],"iteration":33,"passed_time":0.01418454755,"remaining_time":0.4030080275},
{"learn":[0.5153681505],"iteration":34,"passed_time":0.0146170274,"remaining_time":0.403012327},
{"learn":[0.5119407981],"iteration":35,"passed_time":0.01507271451,"remaining_time":0.4036137996},
{"learn":[0.5087566636],"iteration":36,"passed_time":0.01551373563,"remaining_time":0.4037764166},
{"learn":[0.5061696669],"iteration":37,"passed_time":0.01591363367,"remaining_time":0.4028661997},
{"learn":[0.5028667273],"iteration":38,"passed_time":0.01633773891,"remaining_time":0.4025786434},
{"learn":[0.4996598097],"iteration":39,"passed_time":0.0167359287,"remaining_time":0.4016622887},
{"learn":[0.4966892152],"iteration":40,"passed_time":0.01711753592,"remaining_time":0.4003833401},
{"learn":[0.4934337834],"iteration":41,"passed_time":0.01765971899,"remaining_time":0.4028097809},
{"learn":[0.4908029523],"iteration":42,"passed_time":0.01802828516,"remaining_time":0.4012341604},
{"learn":[0.488818971],"iteration":43,"passed_time":0.01829010629,"remaining_time":0.3973941277},
{"learn":[0.4861818096],"iteration":44,"passed_time":0.01867733826,"remaining_time":0.396374623},
{"learn":[0.4833885816],"iteration":45,"passed_time":0.0190720282,"remaining_time":0.3955372805},
{"learn":[0.4807019945],"iteration":46,"passed_time":0.01962041932,"remaining_time":0.3978353109},
{"learn":[0.4783307739],"iteration":47,"passed_time":0.02001531759,"remaining_time":0.3969704656},
{"learn":[0.4751286576],"iteration":48,"passed_time":0.02041275741,"remaining_time":0.3961741285},
{"learn":[0.473015972],"iteration":49,"passed_time":0.02084369567,"remaining_time":0.3960302177},
{"learn":[0.4701670511],"iteration":50,"passed_time":0.0212452603,"remaining_time":0.395328471},
{"learn":[0.4683780414],"iteration":51,"passed_time":0.02153437183,"remaining_time":0.3925881633},
{"learn":[0.4659316242],"iteration":52,"passed_time":0.02194064457,"remaining_time":0.3920337813},
{"learn":[0.464161119],"iteration":53,"passed_time":0.02223275596,"remaining_time":0.389484947},
{"learn":[0.461805692],"iteration":54,"passed_time":0.02260694686,"remaining_time":0.3884284506},
{"learn":[0.4592940747],"iteration":55,"passed_time":0.02299772033,"remaining_time":0.3876758569},
{"learn":[0.457095935],"iteration":56,"passed_time":0.02347344816,"remaining_time":0.3883414319},
{"learn":[0.4549244974],"iteration":57,"passed_time":0.02388942879,"remaining_time":0.3879972744},
{"learn":[0.4524068205],"iteration":58,"passed_time":0.02427757737,"remaining_time":0.3872067848},
{"learn":[0.4500294586],"iteration":59,"passed_time":0.02467789206,"remaining_time":0.3866203089},
{"learn":[0.4479857518],"iteration":60,"passed_time":0.02513378748,"remaining_time":0.3868955155},
{"learn":[0.4463113092],"iteration":61,"passed_time":0.02555576783,"remaining_time":0.3866340358},
{"learn":[0.4445419001],"iteration":62,"passed_time":0.02598783103,"remaining_time":0.3865174234},
{"learn":[0.4428171754],"iteration":63,"passed_time":0.02639239552,"remaining_time":0.3859887845},
{"learn":[0.4411817124],"iteration":64,"passed_time":0.02682279214,"remaining_time":0.3858355484},
{"learn":[0.439263378],"iteration":65,"passed_time":0.02794598981,"remaining_time":0.3954780982},
{"learn":[0.4375817106],"iteration":66,"passed_time":0.02839667715,"remaining_time":0.3954343251},
{"learn":[0.4358938561],"iteration":67,"passed_time":0.028807658,"remaining_time":0.3948343715},
{"learn":[0.4340580721],"iteration":68,"passed_time":0.02923226322,"remaining_time":0.3944237255},
{"learn":[0.4324494751],"iteration":69,"passed_time":0.02965241032,"remaining_time":0.3939534514},
{"learn":[0.4301742888],"iteration":70,"passed_time":0.03010613918,"remaining_time":0.3939239901},
{"learn":[0.4285978063],"iteration":71,"passed_time":0.03051982824,"remaining_time":0.3933666751},
{"learn":[0.4271619041],"iteration":72,"passed_time":0.03092805923,"remaining_time":0.392743985},
{"learn":[0.4255398648],"iteration":73,"passed_time":0.0313086665,"remaining_time":0.3917814213},
{"learn":[0.4238282724],"iteration":74,"passed_time":0.0317043564,"remaining_time":0.3910203956},
{"learn":[0.4222590856],"iteration":75,"passed_time":0.03208442202,"remaining_time":0.3900790257},
{"learn":[0.420807604],"iteration":76,"passed_time":0.03249961102,"remaining_time":0.3895732593},
{"learn":[0.4188513667],"iteration":77,"passed_time":0.03293421577,"remaining_time":0.3892993197},
{"learn":[0.4174828009],"iteration":78,"passed_time":0.03343248423,"remaining_time":0.3897635186},
{"learn":[0.4158226489],"iteration":79,"passed_time":0.03383867364,"remaining_time":0.3891447468},
{"learn":[0.4141383266],"iteration":80,"passed_time":0.0342973606,"remaining_time":0.3891268444},
{"learn":[0.4126432165],"iteration":81,"passed_time":0.03474329816,"remaining_time":0.3889554599},
{"learn":[0.411301802],"iteration":82,"passed_time":0.03521060973,"remaining_time":0.3890136038},
{"learn":[0.4099877763],"iteration":83,"passed_time":0.03564225628,"remaining_time":0.3886703185},
{"learn":[0.4087364012],"iteration":84,"passed_time":0.03604877901,"remaining_time":0.3880545035},
{"learn":[0.4075988045],"iteration":85,"passed_time":0.03644584385,"remaining_time":0.3873430381},
{"learn":[0.4069240607],"iteration":86,"passed_time":0.03671983109,"remaining_time":0.3853471929},
{"learn":[0.4056566873],"iteration":87,"passed_time":0.03711643761,"remaining_time":0.3846612625},
{"learn":[0.4043307687],"iteration":88,"passed_time":0.03750225297,"remaining_time":0.3838713759},
{"learn":[0.4036200963],"iteration":89,"passed_time":0.03789690125,"remaining_time":0.3831797793},
{"learn":[0.402398598],"iteration":90,"passed_time":0.03831313186,"remaining_time":0.3827102952},
{"learn":[0.4010271898],"iteration":91,"passed_time":0.03877765189,"remaining_time":0.3827185643},
{"learn":[0.4000461753],"iteration":92,"passed_time":0.03918754946,"remaining_time":0.3821839501},
{"learn":[0.3989628487],"iteration":93,"passed_time":0.03962498742,"remaining_time":0.3819174319},
{"learn":[0.3978860636],"iteration":94,"passed_time":0.04006167541,"remaining_time":0.381640171},
{"learn":[0.3974367401],"iteration":95,"passed_time":0.04040615936,"remaining_time":0.380491334},
{"learn":[0.3961370003],"iteration":96,"passed_time":0.04087301261,"remaining_time":0.3804982514},
{"learn":[0.3951888335],"iteration":97,"passed_time":0.04126807754,"remaining_time":0.3798347545},
{"learn":[0.3942554434],"iteration":98,"passed_time":0.04169051619,"remaining_time":0.379425809},
{"learn":[0.393403061],"iteration":99,"passed_time":0.04209495569,"remaining_time":0.3788546012},
{"learn":[0.3923621992],"iteration":100,"passed_time":0.04262655592,"remaining_time":0.3794185522},
{"learn":[0.3915702674],"iteration":101,"passed_time":0.04304428646,"remaining_time":0.378958522},
{"learn":[0.3906220349],"iteration":102,"passed_time":0.04349576543,"remaining_time":0.3787932193},
{"learn":[0.3896773136],"iteration":103,"passed_time":0.04393145347,"remaining_time":0.3784863683},
{"learn":[0.3888324545],"iteration":104,"passed_time":0.04432231026,"remaining_time":0.3777949303},
{"learn":[0.3878804422],"iteration":105,"passed_time":0.04471691688,"remaining_time":0.3771407895},
{"learn":[0.3869039246],"iteration":106,"passed_time":0.04509898241,"remaining_time":0.3763868345},
{"learn":[0.3856888052],"iteration":107,"passed_time":0.0455207961,"remaining_time":0.3759680566},
{"learn":[0.3847150362],"iteration":108,"passed_time":0.0459056115,"remaining_time":0.3752467876},
{"learn":[0.3838159789],"iteration":109,"passed_time":0.04645146107,"remaining_time":0.3758345487},
{"learn":[0.3830372731],"iteration":110,"passed_time":0.04686769168,"remaining_time":0.3753637649},
{"learn":[0.3822662711],"iteration":111,"passed_time":0.04727750593,"remaining_time":0.3748430827},
{"learn":[0.3816785774],"iteration":112,"passed_time":0.0476523218,"remaining_time":0.374049641},
{"learn":[0.3810124815],"iteration":113,"passed_time":0.048070094,"remaining_time":0.3735973973},
{"learn":[0.3797753977],"iteration":114,"passed_time":0.04848936614,"remaining_time":0.3731572959},
{"learn":[0.3789290872],"iteration":115,"passed_time":0.04894917805,"remaining_time":0.3730264948},
{"learn":[0.3781786569],"iteration":116,"passed_time":0.04931561931,"remaining_time":0.3721854005},
{"learn":[0.3774119508],"iteration":117,"passed_time":0.04970718441,"remaining_time":0.3715401411},
{"learn":[0.3766890978],"iteration":118,"passed_time":0.0501909952,"remaining_time":0.3715820737},
{"learn":[0.3762970119],"iteration":119,"passed_time":0.05046473245,"remaining_time":0.3700747046},
{"learn":[0.3757518745],"iteration":120,"passed_time":0.05085633921,"remaining_time":0.3694439848},
{"learn":[0.3749854548],"iteration":121,"passed_time":0.05125657056,"remaining_time":0.3688792537},
{"learn":[0.37431339],"iteration":122,"passed_time":0.05169321689,"remaining_time":0.3685768391},
{"learn":[0.3735774436],"iteration":123,"passed_time":0.05210386442,"remaining_time":0.3680885906},
{"learn":[0.3729569427],"iteration":124,"passed_time":0.05265054729,"remaining_time":0.368553831},
{"learn":[0.3721156512],"iteration":125,"passed_time":0.05308831856,"remaining_time":0.3682475431},
{"learn":[0.3711593852],"iteration":126,"passed_time":0.05349446631,"remaining_time":0.3677218039},
{"learn":[0.3703840977],"iteration":127,"passed_time":0.05391990483,"remaining_time":0.3673293516},
{"learn":[0.3700773196],"iteration":128,"passed_time":0.05418243426,"remaining_time":0.365836436},
{"learn":[0.3692374046],"iteration":129,"passed_time":0.05468086938,"remaining_time":0.3659412027},
{"learn":[0.3682237988],"iteration":130,"passed_time":0.05506805967,"remaining_time":0.3652988081},
{"learn":[0.3675727517],"iteration":131,"passed_time":0.05552095524,"remaining_time":0.365092342},
{"learn":[0.3669391187],"iteration":132,"passed_time":0.05606122174,"remaining_time":0.3654517237},
{"learn":[0.3663417105],"iteration":133,"passed_time":0.05652607508,"remaining_time":0.3653103061},
{"learn":[0.3657196491],"iteration":134,"passed_time":0.0569150153,"remaining_time":0.3646776906},
{"learn":[0.3647535795],"iteration":135,"passed_time":0.05756744324,"remaining_time":0.3657225806},
{"learn":[0.3643654717],"iteration":136,"passed_time":0.05863376856,"remaining_time":0.3693499436},
{"learn":[0.3635905147],"iteration":137,"passed_time":0.05908008111,"remaining_time":0.3690364487},
{"learn":[0.3630026825],"iteration":138,"passed_time":0.05960280676,"remaining_time":0.3691943641},
{"learn":[0.3623457387],"iteration":139,"passed_time":0.06000378808,"remaining_time":0.3685946982},
{"learn":[0.3615654161],"iteration":140,"passed_time":0.06041168574,"remaining_time":0.3680399862},
{"learn":[0.361017909],"iteration":141,"passed_time":0.06082566646,"remaining_time":0.3675240973},
{"learn":[0.360585478],"iteration":142,"passed_time":0.06120210725,"remaining_time":0.3667846568},
{"learn":[0.3598843473],"iteration":143,"passed_time":0.0615789647,"remaining_time":0.3660527346},
{"learn":[0.3591727518],"iteration":144,"passed_time":0.06201011128,"remaining_time":0.3656458286},
{"learn":[0.3587278594],"iteration":145,"passed_time":0.06246150692,"remaining_time":0.3653570336},
{"learn":[0.3581336398],"iteration":146,"passed_time":0.06284290582,"remaining_time":0.3646598548},
{"learn":[0.3575727206],"iteration":147,"passed_time":0.0633426742,"remaining_time":0.3646483677},
{"learn":[0.3571212978],"iteration":148,"passed_time":0.06374453048,"remaining_time":0.3640711103},
{"learn":[0.356579552],"iteration":149,"passed_time":0.06417234389,"remaining_time":0.363643282},
{"learn":[0.3560101743],"iteration":150,"passed_time":0.06455990916,"remaining_time":0.3629891581},
{"learn":[0.3555725591],"iteration":151,"passed_time":0.06495501576,"remaining_time":0.3623806142},
{"learn":[0.3549545381],"iteration":152,"passed_time":0.06541670258,"remaining_time":0.362143445},
{"learn":[0.3542177857],"iteration":153,"passed_time":0.06580089302,"remaining_time":0.3614776331},
{"learn":[0.3538433582],"iteration":154,"passed_time":0.06618229192,"remaining_time":0.3608002366},
{"learn":[0.3535701824],"iteration":155,"passed_time":0.06660381395,"remaining_time":0.3603437114},
{"learn":[0.3530536515],"iteration":156,"passed_time":0.06698142136,"remaining_time":0.3596518357},
{"learn":[0.3524884415],"iteration":157,"passed_time":0.06740460998,"remaining_time":0.3592068456},
{"learn":[0.352025835],"iteration":158,"passed_time":0.06781879902,"remaining_time":0.3587145281},
{"learn":[0.3515333495],"iteration":159,"passed_time":0.06822840494,"remaining_time":0.3581991259},
{"learn":[0.3510216235],"iteration":160,"passed_time":0.06868584196,"remaining_time":0.3579342944},
{"learn":[0.3506585407],"iteration":161,"passed_time":0.06921515063,"remaining_time":0.3580388656},
{"learn":[0.3498752016],"iteration":162,"passed_time":0.06973687633,"remaining_time":0.3580967208},
{"learn":[0.3495268313],"iteration":163,"passed_time":0.07079036892,"remaining_time":0.3608582221},
{"learn":[0.3489931702],"iteration":164,"passed_time":0.07133088541,"remaining_time":0.360977511},
{"learn":[0.3485988257],"iteration":165,"passed_time":0.07175065752,"remaining_time":0.3604822191},
{"learn":[0.3480310015],"iteration":166,"passed_time":0.07233658856,"remaining_time":0.3608166363},
{"learn":[0.3474248083],"iteration":167,"passed_time":0.0727549024,"remaining_time":0.3603099929},
{"learn":[0.3468050731],"iteration":168,"passed_time":0.07316259174,"remaining_time":0.3597521523},
{"learn":[0.3464806852],"iteration":169,"passed_time":0.07367202635,"remaining_time":0.3596928345},
{"learn":[0.3462418378],"iteration":170,"passed_time":0.07397734546,"remaining_time":0.3586387098},
{"learn":[0.3457177627],"iteration":171,"passed_time":0.07453644441,"remaining_time":0.3588149766},
{"learn":[0.3453168024],"iteration":172,"passed_time":0.07494021727,"remaining_time":0.3582402294},
{"learn":[0.3445436293],"iteration":173,"passed_time":0.07535973939,"remaining_time":0.3577422111},
{"learn":[0.3443328636],"iteration":174,"passed_time":0.07570843148,"remaining_time":0.356911177},
{"learn":[0.3441807243],"iteration":175,"passed_time":0.07595812818,"remaining_time":0.3556221456},
{"learn":[0.343620152],"iteration":176,"passed_time":0.07651943537,"remaining_time":0.3557937588},
{"learn":[0.3433403805],"iteration":177,"passed_time":0.07693829085,"remaining_time":0.3552992982},
{"learn":[0.3426269151],"iteration":178,"passed_time":0.07732343958,"remaining_time":0.3546510832},
{"learn":[0.3423344942],"iteration":179,"passed_time":0.07774354501,"remaining_time":0.3541650384},
{"learn":[0.3419118501],"iteration":180,"passed_time":0.07827960337,"remaining_time":0.3542043931},
{"learn":[0.3413730596],"iteration":181,"passed_time":0.07878599645,"remaining_time":0.3541040939},
{"learn":[0.3410590429],"iteration":182,"passed_time":0.07923897534,"remaining_time":0.3537608899},
{"learn":[0.3406893379],"iteration":183,"passed_time":0.07965749751,"remaining_time":0.3532636846},
{"learn":[0.3402656806],"iteration":184,"passed_time":0.08007522805,"remaining_time":0.3527638425},
{"learn":[0.3397415519],"iteration":185,"passed_time":0.08049162532,"remaining_time":0.3522590485},
{"learn":[0.3394198758],"iteration":186,"passed_time":0.08100972619,"remaining_time":0.3521973657},
{"learn":[0.3389230437],"iteration":187,"passed_time":0.08139708314,"remaining_time":0.3515661251},
{"learn":[0.3383695228],"iteration":188,"passed_time":0.08176456602,"remaining_time":0.3508521854},
{"learn":[0.3381094921],"iteration":189,"passed_time":0.08223991888,"remaining_time":0.3506017594},
{"learn":[0.3374223365],"iteration":190,"passed_time":0.08282576659,"remaining_time":0.3508169904},
{"learn":[0.3370982713],"iteration":191,"passed_time":0.08326357953,"remaining_time":0.3504008972},
{"learn":[0.336662042],"iteration":192,"passed_time":0.08371239195,"remaining_time":0.3500305715},
{"learn":[0.336198979],"iteration":193,"passed_time":0.08415953779,"remaining_time":0.3496525127},
{"learn":[0.3357883437],"iteration":194,"passed_time":0.08456835208,"remaining_time":0.3491155047},
{"learn":[0.3353217371],"iteration":195,"passed_time":0.08496654186,"remaining_time":0.3485362227},
{"learn":[0.335019734],"iteration":196,"passed_time":0.08539085543,"remaining_time":0.3480652635},
{"learn":[0.3344844635],"iteration":197,"passed_time":0.08580675272,"remaining_time":0.3475606853},
{"learn":[0.3338836077],"iteration":198,"passed_time":0.086287272,"remaining_time":0.3473171099},
{"learn":[0.3335891454],"iteration":199,"passed_time":0.08666625435,"remaining_time":0.3466650174},
{"learn":[0.3332478283],"iteration":200,"passed_time":0.08705036145,"remaining_time":0.3460360139},
{"learn":[0.3330008591],"iteration":201,"passed_time":0.08746784201,"remaining_time":0.3455412768},
{"learn":[0.3327254391],"iteration":202,"passed_time":0.08787978115,"remaining_time":0.3450255447},
{"learn":[0.3323146636],"iteration":203,"passed_time":0.0883022198,"remaining_time":0.3445517988},
{"learn":[0.3319533689],"iteration":204,"passed_time":0.08873224144,"remaining_time":0.3441079607},
{"learn":[0.3314821509],"iteration":205,"passed_time":0.0891381392,"remaining_time":0.3435712744},
{"learn":[0.3310756807],"iteration":206,"passed_time":0.08957774372,"remaining_time":0.3431649796},
{"learn":[0.3307939062],"iteration":207,"passed_time":0.08999555759,"remaining_time":0.3426753923},
{"learn":[0.3304642797],"iteration":208,"passed_time":0.09052519958,"remaining_time":0.3426097266},
{"learn":[0.330152904],"iteration":209,"passed_time":0.09088868265,"remaining_time":0.3419145681},
{"learn":[0.3297245904],"iteration":210,"passed_time":0.09133312028,"remaining_time":0.3415252697},
{"learn":[0.3293456961],"iteration":211,"passed_time":0.09174105961,"remaining_time":0.3409997876},
{"learn":[0.3289653885],"iteration":212,"passed_time":0.09226116038,"remaining_time":0.3408898273},
{"learn":[0.3284868552],"iteration":213,"passed_time":0.09274667943,"remaining_time":0.3406490188},
{"learn":[0.3281820071],"iteration":214,"passed_time":0.09320624135,"remaining_time":0.3403111603},
{"learn":[0.3278467009],"iteration":215,"passed_time":0.09376296542,"remaining_time":0.3403248374},
{"learn":[0.3274239773],"iteration":216,"passed_time":0.09419190377,"remaining_time":0.3398721689},
{"learn":[0.3270972795],"iteration":217,"passed_time":0.09463104998,"remaining_time":0.3394563352},
{"learn":[0.3266040422],"iteration":218,"passed_time":0.09503161465,"remaining_time":0.3389026988},
{"learn":[0.3263254828],"iteration":219,"passed_time":0.09542230478,"remaining_time":0.3383154442},
{"learn":[0.3258608987],"iteration":220,"passed_time":0.09581936962,"remaining_time":0.3377524386},
{"learn":[0.3254984702],"iteration":221,"passed_time":0.09620193513,"remaining_time":0.337140115},
{"learn":[0.3250743459],"iteration":222,"passed_time":0.09662745697,"remaining_time":0.336679525},
{"learn":[0.3246821692],"iteration":223,"passed_time":0.09710305982,"remaining_time":0.3363927429},
{"learn":[0.3244524739],"iteration":224,"passed_time":0.09754108108,"remaining_time":0.3359748348},
{"learn":[0.3241447218],"iteration":225,"passed_time":0.09803505807,"remaining_time":0.3357483847},
{"learn":[0.3239001774],"iteration":226,"passed_time":0.09844349737,"remaining_time":0.3352282972},
{"learn":[0.3234713852],"iteration":227,"passed_time":0.09886468609,"remaining_time":0.3347523582},
{"learn":[0.3231790404],"iteration":228,"passed_time":0.0992929578,"remaining_time":0.3343007444},
{"learn":[0.3228585505],"iteration":229,"passed_time":0.09973193735,"remaining_time":0.3338851816},
{"learn":[0.3223565974],"iteration":230,"passed_time":0.1002557879,"remaining_time":0.3337519521},
{"learn":[0.3221671162],"iteration":231,"passed_time":0.1007191414,"remaining_time":0.3334150887},
{"learn":[0.3218497682],"iteration":232,"passed_time":0.1011272474,"remaining_time":0.3328952735},
{"learn":[0.3216648265],"iteration":233,"passed_time":0.1015713517,"remaining_time":0.3324942537},
{"learn":[0.3213875369],"iteration":234,"passed_time":0.1020045815,"remaining_time":0.3320574674},
{"learn":[0.321074773],"iteration":235,"passed_time":0.1025333902,"remaining_time":0.3319301275},
{"learn":[0.3205732976],"iteration":236,"passed_time":0.1029482042,"remaining_time":0.3314324042},
{"learn":[0.3201805063],"iteration":237,"passed_time":0.1033606433,"remaining_time":0.330927774},
{"learn":[0.3198039882],"iteration":238,"passed_time":0.1037911233,"remaining_time":0.330481359},
{"learn":[0.3195447035],"iteration":239,"passed_time":0.1042123953,"remaining_time":0.3300059184},
{"learn":[0.3191091516],"iteration":240,"passed_time":0.1046972477,"remaining_time":0.329731166},
{"learn":[0.3186615145],"iteration":241,"passed_time":0.1051307692,"remaining_time":0.3292938969},
{"learn":[0.3183106651],"iteration":242,"passed_time":0.1055528745,"remaining_time":0.3288210947},
{"learn":[0.317935018],"iteration":243,"passed_time":0.106036352,"remaining_time":0.3285388611},
{"learn":[0.3176716926],"iteration":244,"passed_time":0.106458749,"remaining_time":0.3280667571},
{"learn":[0.3171327133],"iteration":245,"passed_time":0.1068718547,"remaining_time":0.3275665792},
{"learn":[0.3167408877],"iteration":246,"passed_time":0.1074170793,"remaining_time":0.3274698816},
{"learn":[0.3164193524],"iteration":247,"passed_time":0.1078165607,"remaining_time":0.3269276358},
{"learn":[0.3160726957],"iteration":248,"passed_time":0.1082609567,"remaining_time":0.3265220019},
{"learn":[0.3157855195],"iteration":249,"passed_time":0.1086514802,"remaining_time":0.3259544405},
{"learn":[0.3154897858],"iteration":250,"passed_time":0.1090542114,"remaining_time":0.3254247185},
{"learn":[0.3150613683],"iteration":251,"passed_time":0.1094789416,"remaining_time":0.3249613029},
{"learn":[0.3146671726],"iteration":252,"passed_time":0.1101308279,"remaining_time":0.3251688872},
{"learn":[0.3143925247],"iteration":253,"passed_time":0.1105960146,"remaining_time":0.3248213657},
{"learn":[0.3141808909],"iteration":254,"passed_time":0.1110153701,"remaining_time":0.3243390223},
{"learn":[0.3140883739],"iteration":255,"passed_time":0.1113046899,"remaining_time":0.323479255},
{"learn":[0.3137024128],"iteration":256,"passed_time":0.1117061712,"remaining_time":0.3229481915},
{"learn":[0.3133146152],"iteration":257,"passed_time":0.1120819454,"remaining_time":0.3223441995},
{"learn":[0.3129342471],"iteration":258,"passed_time":0.1124664275,"remaining_time":0.3217668832},
{"learn":[0.3126974607],"iteration":259,"passed_time":0.1128881578,"remaining_time":0.3212970645},
{"learn":[0.3125739901],"iteration":260,"passed_time":0.1133689271,"remaining_time":0.3209947782},
{"learn":[0.3122118896],"iteration":261,"passed_time":0.1137456595,"remaining_time":0.3203980791},
{"learn":[0.3119377847],"iteration":262,"passed_time":0.1141676399,"remaining_time":0.3199298501},
{"learn":[0.3114101377],"iteration":263,"passed_time":0.1145853287,"remaining_time":0.3194500074},
{"learn":[0.3110723071],"iteration":264,"passed_time":0.114966686,"remaining_time":0.3188698649},
{"learn":[0.3106782953],"iteration":265,"passed_time":0.115351793,"remaining_time":0.3183015643},
{"learn":[0.3103183756],"iteration":266,"passed_time":0.115767107,"remaining_time":0.3178175635},
{"learn":[0.3102347433],"iteration":267,"passed_time":0.1161016331,"remaining_time":0.3171134158},
{"learn":[0.3100606647],"iteration":268,"passed_time":0.1165910686,"remaining_time":0.3168329784},
{"learn":[0.3097031756],"iteration":269,"passed_time":0.1169894668,"remaining_time":0.3163048545},
{"learn":[0.3092867232],"iteration":270,"passed_time":0.1175685231,"remaining_time":0.3162636655},
{"learn":[0.3090631598],"iteration":271,"passed_time":0.1180137524,"remaining_time":0.3158603372},
{"learn":[0.3088304354],"iteration":272,"passed_time":0.1184528986,"remaining_time":0.3154405028},
{"learn":[0.3084126358],"iteration":273,"passed_time":0.1188470885,"remaining_time":0.3149014098},
{"learn":[0.3083244037],"iteration":274,"passed_time":0.1192498198,"remaining_time":0.3143858885},
{"learn":[0.3080837445],"iteration":275,"passed_time":0.1196200525,"remaining_time":0.3137859349},
{"learn":[0.3077426281],"iteration":276,"passed_time":0.1200072845,"remaining_time":0.3132320097},
{"learn":[0.3077235089],"iteration":277,"passed_time":0.1202319824,"remaining_time":0.3122571628},
{"learn":[0.3072552699],"iteration":278,"passed_time":0.1206225058,"remaining_time":0.3117162248},
{"learn":[0.3069075894],"iteration":279,"passed_time":0.1210264454,"remaining_time":0.3112108595},
{"learn":[0.306428892],"iteration":280,"passed_time":0.1214716746,"remaining_time":0.3108118649},
{"learn":[0.3061291093],"iteration":281,"passed_time":0.1219342781,"remaining_time":0.3104567789},
{"learn":[0.3059280169],"iteration":282,"passed_time":0.1222860533,"remaining_time":0.3098201422},
{"learn":[0.3055466222],"iteration":283,"passed_time":0.1227379073,"remaining_time":0.3094378226},
{"learn":[0.3052828395],"iteration":284,"passed_time":0.1231046819,"remaining_time":0.3088415703},
{"learn":[0.3049724578],"iteration":285,"passed_time":0.123516496,"remaining_time":0.3083593642},
{"learn":[0.304727364],"iteration":286,"passed_time":0.1239013531,"remaining_time":0.3078106786},
{"learn":[0.3044648413],"iteration":287,"passed_time":0.1243456657,"remaining_time":0.3074101181},
{"learn":[0.3043239582],"iteration":288,"passed_time":0.1247782289,"remaining_time":0.3069803486},
{"learn":[0.30419915],"iteration":289,"passed_time":0.1251733355,"remaining_time":0.3064588559},
{"learn":[0.3041167602],"iteration":290,"passed_time":0.125700311,"remaining_time":0.3062595205},
{"learn":[0.3036494302],"iteration":291,"passed_time":0.1260949176,"remaining_time":0.3057369919},
{"learn":[0.3033465106],"iteration":292,"passed_time":0.1265518546,"remaining_time":0.3053657379},
{"learn":[0.3032113373],"iteration":293,"passed_time":0.1269109212,"remaining_time":0.3047588789},
{"learn":[0.3029236878],"iteration":294,"passed_time":0.1273434844,"remaining_time":0.3043293441},
{"learn":[0.3025699953],"iteration":295,"passed_time":0.1277363411,"remaining_time":0.3038053518},
{"learn":[0.3024461551],"iteration":296,"passed_time":0.1283143142,"remaining_time":0.3037204137},
{"learn":[0.3021439379],"iteration":297,"passed_time":0.1286795888,"remaining_time":0.303131112},
{"learn":[0.3019537918],"iteration":298,"passed_time":0.1291802322,"remaining_time":0.3028606781},
{"learn":[0.3017711553],"iteration":299,"passed_time":0.1295973377,"remaining_time":0.3023937881},
{"learn":[0.3016499439],"iteration":300,"passed_time":0.1300291093,"remaining_time":0.3019612871},
{"learn":[0.3015366072],"iteration":301,"passed_time":0.1304470482,"remaining_time":0.3014968199},
{"learn":[0.3012460229],"iteration":302,"passed_time":0.1309848148,"remaining_time":0.3013083033},
{"learn":[0.3010103194],"iteration":303,"passed_time":0.1313900459,"remaining_time":0.3008140525},
{"learn":[0.3008197924],"iteration":304,"passed_time":0.1318112763,"remaining_time":0.3003568427},
{"learn":[0.3006268884],"iteration":305,"passed_time":0.1323595007,"remaining_time":0.3001878873},
{"learn":[0.3005757436],"iteration":306,"passed_time":0.1326042393,"remaining_time":0.2993313937},
{"learn":[0.3003211262],"iteration":307,"passed_time":0.1330165951,"remaining_time":0.298855467},
{"learn":[0.2999573432],"iteration":308,"passed_time":0.1334924896,"remaining_time":0.2985220399},
{"learn":[0.2995862083],"iteration":309,"passed_time":0.1339060537,"remaining_time":0.2980489582},
{"learn":[0.299130986],"iteration":310,"passed_time":0.1343650323,"remaining_time":0.2976768722},
{"learn":[0.2990131935],"iteration":311,"passed_time":0.1347432647,"remaining_time":0.2971261734},
{"learn":[0.2986705279],"iteration":312,"passed_time":0.135157912,"remaining_time":0.2966565034},
{"learn":[0.2985815701],"iteration":313,"passed_time":0.1354643978,"remaining_time":0.2959508817},
{"learn":[0.2981721451],"iteration":314,"passed_time":0.13588242,"remaining_time":0.2954903418},
{"learn":[0.2977327371],"iteration":315,"passed_time":0.1362853595,"remaining_time":0.2949974238},
{"learn":[0.2975198844],"iteration":316,"passed_time":0.1367744617,"remaining_time":0.2946907172},
{"learn":[0.2971586013],"iteration":317,"passed_time":0.137220316,"remaining_time":0.2942901116},
{"learn":[0.2969451383],"iteration":318,"passed_time":0.1376302135,"remaining_time":0.2938124621},
{"learn":[0.2962337042],"iteration":319,"passed_time":0.1380026545,"remaining_time":0.2932556409},
{"learn":[0.2960418851],"iteration":320,"passed_time":0.1383986361,"remaining_time":0.2927497629},
{"learn":[0.2958187231],"iteration":321,"passed_time":0.1387965759,"remaining_time":0.2922486908},
{"learn":[0.2956128953],"iteration":322,"passed_time":0.139195099,"remaining_time":0.2917494799},
{"learn":[0.2954042079],"iteration":323,"passed_time":0.1403335043,"remaining_time":0.2927945953},
{"learn":[0.2951898248],"iteration":324,"passed_time":0.1407062786,"remaining_time":0.292236117},
{"learn":[0.2948804252],"iteration":325,"passed_time":0.1411893394,"remaining_time":0.2919067937},
{"learn":[0.2947153716],"iteration":326,"passed_time":0.1416545677,"remaining_time":0.291539829},
{"learn":[0.2945417316],"iteration":327,"passed_time":0.1420668402,"remaining_time":0.2910637702},
{"learn":[0.2943444769],"iteration":328,"passed_time":0.1424904038,"remaining_time":0.2906111275},
{"learn":[0.2941830647],"iteration":329,"passed_time":0.1428630114,"remaining_time":0.290055205},
{"learn":[0.2939393161],"iteration":330,"passed_time":0.1432909082,"remaining_time":0.2896121377},
{"learn":[0.2937377717],"iteration":331,"passed_time":0.1437054305,"remaining_time":0.2891422518},
{"learn":[0.2935412388],"iteration":332,"passed_time":0.1441399103,"remaining_time":0.2887126732},
{"learn":[0.2933512192],"iteration":333,"passed_time":0.1451433635,"remaining_time":0.2894176051},
{"learn":[0.2931110823],"iteration":334,"passed_time":0.1454940972,"remaining_time":0.2888166407},
{"learn":[0.2928181552],"iteration":335,"passed_time":0.1459856993,"remaining_time":0.2884955486},
{"learn":[0.2927823816],"iteration":336,"passed_time":0.1462516452,"remaining_time":0.2877294979},
{"learn":[0.2925661089],"iteration":337,"passed_time":0.1466377523,"remaining_time":0.2872017515},
{"learn":[0.2922925281],"iteration":338,"passed_time":0.1470619408,"remaining_time":0.2867490941},
{"learn":[0.2920181805],"iteration":339,"passed_time":0.1475757502,"remaining_time":0.286470574},
{"learn":[0.291877796],"iteration":340,"passed_time":0.1480206045,"remaining_time":0.2860574146},
{"learn":[0.2915855233],"iteration":341,"passed_time":0.1485282059,"remaining_time":0.2857647937},
{"learn":[0.2911782784],"iteration":342,"passed_time":0.1490442652,"remaining_time":0.2854871201},
{"learn":[0.2908989232],"iteration":343,"passed_time":0.1495542414,"remaining_time":0.2851964603},
{"learn":[0.2908445071],"iteration":344,"passed_time":0.149863602,"remaining_time":0.2845236501},
{"learn":[0.2907125151],"iteration":345,"passed_time":0.1502741662,"remaining_time":0.2840442332},
{"learn":[0.2904578302],"iteration":346,"passed_time":0.1507111458,"remaining_time":0.2836149229},
{"learn":[0.2902756869],"iteration":347,"passed_time":0.15115875,"remaining_time":0.2832054741},
{"learn":[0.2900852206],"iteration":348,"passed_time":0.1516561851,"remaining_time":0.282888758},
{"learn":[0.2898967092],"iteration":349,"passed_time":0.1520749573,"remaining_time":0.2824249207},
{"learn":[0.2897668398],"iteration":350,"passed_time":0.1530222465,"remaining_time":0.2829385698},
{"learn":[0.2895044634],"iteration":351,"passed_time":0.153433019,"remaining_time":0.2824562396},
{"learn":[0.2892505034],"iteration":352,"passed_time":0.1538503746,"remaining_time":0.2819863806},
{"learn":[0.2890896012],"iteration":353,"passed_time":0.1542564807,"remaining_time":0.2814962896},
{"learn":[0.2888910003],"iteration":354,"passed_time":0.1547017933,"remaining_time":0.2810779061},
{"learn":[0.2886898312],"iteration":355,"passed_time":0.1551838125,"remaining_time":0.2807257731},
{"learn":[0.2885262266],"iteration":356,"passed_time":0.1556283334,"remaining_time":0.2803053737},
{"learn":[0.2883819455],"iteration":357,"passed_time":0.1567978623,"remaining_time":0.2811849933},
{"learn":[0.2883005584],"iteration":358,"passed_time":0.1571253887,"remaining_time":0.2805497887},
{"learn":[0.2880666182],"iteration":359,"passed_time":0.1576150742,"remaining_time":0.2802045764},
{"learn":[0.2878831148],"iteration":360,"passed_time":0.1581091762,"remaining_time":0.2798663811},
{"learn":[0.2877740417],"iteration":361,"passed_time":0.1585379896,"remaining_time":0.2794122578},
{"learn":[0.2876746825],"iteration":362,"passed_time":0.1589000977,"remaining_time":0.2788412183},
{"learn":[0.287513023],"iteration":363,"passed_time":0.1593353691,"remaining_time":0.2783991614},
{"learn":[0.2871838686],"iteration":364,"passed_time":0.1597388503,"remaining_time":0.2779018354},
{"learn":[0.2870137213],"iteration":365,"passed_time":0.1602013287,"remaining_time":0.2775072197},
{"learn":[0.2867811341],"iteration":366,"passed_time":0.1605899773,"remaining_time":0.2769848927},
{"learn":[0.2864090329],"iteration":367,"passed_time":0.1610424146,"remaining_time":0.2765728424},
{"learn":[0.2861770876],"iteration":368,"passed_time":0.1615839727,"remaining_time":0.2763129722},
{"learn":[0.2858880513],"iteration":369,"passed_time":0.161962455,"remaining_time":0.2757739099},
{"learn":[0.2857333055],"iteration":370,"passed_time":0.1623431456,"remaining_time":0.2752394571},
{"learn":[0.2854813173],"iteration":371,"passed_time":0.1627972078,"remaining_time":0.2748296949},
{"learn":[0.2853277098],"iteration":372,"passed_time":0.1632992261,"remaining_time":0.2745003077},
{"learn":[0.285255459],"iteration":373,"passed_time":0.1637076654,"remaining_time":0.2740133651},
{"learn":[0.284955111],"iteration":374,"passed_time":0.1641111883,"remaining_time":0.2735186471},
{"learn":[0.2848106535],"iteration":375,"passed_time":0.1645678753,"remaining_time":0.2731126442},
{"learn":[0.2846811468],"iteration":376,"passed_time":0.1650048133,"remaining_time":0.2726737366},
{"learn":[0.284645737],"iteration":377,"passed_time":0.165269051,"remaining_time":0.2719506606},
{"learn":[0.2845272602],"iteration":378,"passed_time":0.1657649862,"remaining_time":0.2716096476},
{"learn":[0.2843055129],"iteration":379,"passed_time":0.1661279693,"remaining_time":0.2710508973},
{"learn":[0.2841579519],"iteration":380,"passed_time":0.1664776614,"remaining_time":0.2704715811},
{"learn":[0.2839080117],"iteration":381,"passed_time":0.1669312236,"remaining_time":0.2700615083},
{"learn":[0.28367016],"iteration":382,"passed_time":0.1673120808,"remaining_time":0.2695340832},
{"learn":[0.2832258392],"iteration":383,"passed_time":0.1679179693,"remaining_time":0.269368409},
{"learn":[0.2830865135],"iteration":384,"passed_time":0.1684562359,"remaining_time":0.2690924287},
{"learn":[0.2828598632],"iteration":385,"passed_time":0.1688375931,"remaining_time":0.2685654978},
{"learn":[0.2824063917],"iteration":386,"passed_time":0.1692358662,"remaining_time":0.2680661136},
{"learn":[0.2819948803],"iteration":387,"passed_time":0.1702612351,"remaining_time":0.2685563811},
{"learn":[0.2817761113],"iteration":388,"passed_time":0.1706737576,"remaining_time":0.2680762619},
{"learn":[0.2815354027],"iteration":389,"passed_time":0.1710589479,"remaining_time":0.2675537391},
{"learn":[0.2813024437],"iteration":390,"passed_time":0.1714594293,"remaining_time":0.2670557351},
{"learn":[0.2812389224],"iteration":391,"passed_time":0.1719362821,"remaining_time":0.2666766824},
{"learn":[0.2811316068],"iteration":392,"passed_time":0.1723480962,"remaining_time":0.2661966779},
{"learn":[0.2809043217],"iteration":393,"passed_time":0.1728008251,"remaining_time":0.2657799493},
{"learn":[0.2806783258],"iteration":394,"passed_time":0.1731845156,"remaining_time":0.265257296},
{"learn":[0.2804717571],"iteration":395,"passed_time":0.1736812008,"remaining_time":0.2649076901},
{"learn":[0.2803846223],"iteration":396,"passed_time":0.1741339297,"remaining_time":0.2644905784},
{"learn":[0.2799902163],"iteration":397,"passed_time":0.1746021579,"remaining_time":0.2640967313},
{"learn":[0.27977551],"iteration":398,"passed_time":0.1749705991,"remaining_time":0.2635522056},
{"learn":[0.2794464692],"iteration":399,"passed_time":0.1754462019,"remaining_time":0.2631693028},
{"learn":[0.2791957055],"iteration":400,"passed_time":0.1758392253,"remaining_time":0.2626625834},
{"learn":[0.2790173526],"iteration":401,"passed_time":0.1762551642,"remaining_time":0.2621905179},
{"learn":[0.278785138],"iteration":402,"passed_time":0.1766551456,"remaining_time":0.2616950916},
{"learn":[0.2785005238],"iteration":403,"passed_time":0.1770487106,"remaining_time":0.261190672},
{"learn":[0.2782392929],"iteration":404,"passed_time":0.1774350259,"remaining_time":0.2606761492},
{"learn":[0.2780651634],"iteration":405,"passed_time":0.1779641263,"remaining_time":0.2603711601},
{"learn":[0.2779011779],"iteration":406,"passed_time":0.1784143136,"remaining_time":0.2599500933},
{"learn":[0.2777115377],"iteration":407,"passed_time":0.1789645797,"remaining_time":0.259674096},
{"learn":[0.2772888019],"iteration":408,"passed_time":0.1794254332,"remaining_time":0.2592675575},
{"learn":[0.277212359],"iteration":409,"passed_time":0.1798904532,"remaining_time":0.2588667497},
{"learn":[0.2770108565],"iteration":410,"passed_time":0.1804645515,"remaining_time":0.2586219484},
{"learn":[0.2768084592],"iteration":411,"passed_time":0.1809381544,"remaining_time":0.2582321233},
{"learn":[0.2766399773],"iteration":412,"passed_time":0.1814580885,"remaining_time":0.2579077432},
{"learn":[0.2765041104],"iteration":413,"passed_time":0.1818874018,"remaining_time":0.2574541485},
{"learn":[0.2763722266],"iteration":414,"passed_time":0.1823425473,"remaining_time":0.2570370847},
{"learn":[0.2760464261],"iteration":415,"passed_time":0.1827445286,"remaining_time":0.2565452036},
{"learn":[0.2759236652],"iteration":416,"passed_time":0.1831202194,"remaining_time":0.2560169974},
{"learn":[0.2757798915],"iteration":417,"passed_time":0.1836671106,"remaining_time":0.2557278908},
{"learn":[0.2755364391],"iteration":418,"passed_time":0.1840698418,"remaining_time":0.2552376566},
{"learn":[0.2753317762],"iteration":419,"passed_time":0.184452074,"remaining_time":0.2547195308},
{"learn":[0.2752349588],"iteration":420,"passed_time":0.1848794291,"remaining_time":0.254264108},
{"learn":[0.2751070826],"iteration":421,"passed_time":0.1853688647,"remaining_time":0.2538938478},
{"learn":[0.2749897498],"iteration":422,"passed_time":0.1857592215,"remaining_time":0.2533878742},
{"learn":[0.2746101765],"iteration":423,"passed_time":0.1861649526,"remaining_time":0.2529033318},
{"learn":[0.2744690442],"iteration":424,"passed_time":0.1865997656,"remaining_time":0.2524585065},
{"learn":[0.2743648465],"iteration":425,"passed_time":0.1869929973,"remaining_time":0.2519577006},
{"learn":[0.2740507962],"iteration":426,"passed_time":0.1874362267,"remaining_time":0.2515244915},
{"learn":[0.2738479541],"iteration":427,"passed_time":0.1878536656,"remaining_time":0.251056768},
{"learn":[0.2737134062],"iteration":428,"passed_time":0.1883890573,"remaining_time":0.2507462744},
{"learn":[0.2736386417],"iteration":429,"passed_time":0.1888873257,"remaining_time":0.2503855248},
{"learn":[0.2734740027],"iteration":430,"passed_time":0.1892746827,"remaining_time":0.2498777134},
{"learn":[0.2733211515],"iteration":431,"passed_time":0.1898214489,"remaining_time":0.2495800532},
{"learn":[0.2732112275],"iteration":432,"passed_time":0.1903393414,"remaining_time":0.2492434332},
{"learn":[0.2731193816],"iteration":433,"passed_time":0.1907830291,"remaining_time":0.2488092039},
{"learn":[0.2729566999],"iteration":434,"passed_time":0.1911850104,"remaining_time":0.2483207606},
{"learn":[0.2727120983],"iteration":435,"passed_time":0.191607949,"remaining_time":0.2478598239},
{"learn":[0.27244657],"iteration":436,"passed_time":0.1920088887,"remaining_time":0.2473707193},
{"learn":[0.2723217197],"iteration":437,"passed_time":0.1924179113,"remaining_time":0.2468923884},
{"learn":[0.2721546692],"iteration":438,"passed_time":0.1928231841,"remaining_time":0.2464095815},
{"learn":[0.2720546277],"iteration":439,"passed_time":0.1932724548,"remaining_time":0.2459831243},
{"learn":[0.2718781681],"iteration":440,"passed_time":0.1937988469,"remaining_time":0.2456543207},
{"learn":[0.2716717993],"iteration":441,"passed_time":0.1942336184,"remaining_time":0.2452089571},
{"learn":[0.2713901474],"iteration":442,"passed_time":0.1948054667,"remaining_time":0.2449359931},
{"learn":[0.2711029604],"iteration":443,"passed_time":0.1952116561,"remaining_time":0.2444542361},
{"learn":[0.270934681],"iteration":444,"passed_time":0.1956214287,"remaining_time":0.2439772875},
{"learn":[0.2708085488],"iteration":445,"passed_time":0.1960367844,"remaining_time":0.2435075752},
{"learn":[0.2705584495],"iteration":446,"passed_time":0.1964291411,"remaining_time":0.2430096533},
{"learn":[0.2701891296],"iteration":447,"passed_time":0.1976170857,"remaining_time":0.2434924806},
{"learn":[0.270115809],"iteration":448,"passed_time":0.1980237335,"remaining_time":0.2430090805},
{"learn":[0.2700379049],"iteration":449,"passed_time":0.1984145486,"remaining_time":0.2425066705},
{"learn":[0.2696892038],"iteration":450,"passed_time":0.1988219879,"remaining_time":0.242024992},
{"learn":[0.2695357254],"iteration":451,"passed_time":0.1992639674,"remaining_time":0.2415855179},
{"learn":[0.2693721306],"iteration":452,"passed_time":0.1997469449,"remaining_time":0.2411955383},
{"learn":[0.2691660604],"iteration":453,"passed_time":0.2002177979,"remaining_time":0.2407905675},
{"learn":[0.2689906447],"iteration":454,"passed_time":0.2006112379,"remaining_time":0.2402925817},
{"learn":[0.2688690701],"iteration":455,"passed_time":0.2011767532,"remaining_time":0.2400003372},
{"learn":[0.2685026725],"iteration":456,"passed_time":0.2015828593,"remaining_time":0.2395174893},
{"learn":[0.2684045743],"iteration":457,"passed_time":0.2019526754,"remaining_time":0.2389920308},
{"learn":[0.2683368325],"iteration":458,"passed_time":0.2024026128,"remaining_time":0.2385616852},
{"learn":[0.2682211402],"iteration":459,"passed_time":0.2027784286,"remaining_time":0.2380442423},
{"learn":[0.2681132201],"iteration":460,"passed_time":0.2031727853,"remaining_time":0.2375490917},
{"learn":[0.2679020721],"iteration":461,"passed_time":0.203629764,"remaining_time":0.2371273009},
{"learn":[0.2674326599],"iteration":462,"passed_time":0.2041459066,"remaining_time":0.2367739781},
{"learn":[0.2672994284],"iteration":463,"passed_time":0.2045359718,"remaining_time":0.2362743122},
{"learn":[0.2670946559],"iteration":464,"passed_time":0.2049370364,"remaining_time":0.2357877731},
{"learn":[0.2668925728],"iteration":465,"passed_time":0.2053633915,"remaining_time":0.2353305817},
{"learn":[0.2666171373],"iteration":466,"passed_time":0.2057303745,"remaining_time":0.2348057593},
{"learn":[0.2663794334],"iteration":467,"passed_time":0.2061282309,"remaining_time":0.2343167069},
{"learn":[0.2660845503],"iteration":468,"passed_time":0.2064991303,"remaining_time":0.2337975228},
{"learn":[0.26591179],"iteration":469,"passed_time":0.2069192774,"remaining_time":0.2333345043},
{"learn":[0.2657381121],"iteration":470,"passed_time":0.2073156339,"remaining_time":0.2328449477},
{"learn":[0.2656190263],"iteration":471,"passed_time":0.2077381559,"remaining_time":0.2323850558},
{"learn":[0.2654511065],"iteration":472,"passed_time":0.2081902599,"remaining_time":0.2319582811},
{"learn":[0.2651948316],"iteration":473,"passed_time":0.2086215731,"remaining_time":0.231508328},
{"learn":[0.2649956799],"iteration":474,"passed_time":0.2090583444,"remaining_time":0.2310644859},
{"learn":[0.2647196918],"iteration":475,"passed_time":0.2094840329,"remaining_time":0.2306084732},
{"learn":[0.2645535307],"iteration":476,"passed_time":0.209919596,"remaining_time":0.2301634144},
{"learn":[0.2643754999],"iteration":477,"passed_time":0.2103579505,"remaining_time":0.2297214439},
{"learn":[0.2641808501],"iteration":478,"passed_time":0.2107838474,"remaining_time":0.2292659384},
{"learn":[0.26394808],"iteration":479,"passed_time":0.2112222019,"remaining_time":0.2288240521},
{"learn":[0.2637359041],"iteration":480,"passed_time":0.2115920597,"remaining_time":0.2283082723},
{"learn":[0.2635250615],"iteration":481,"passed_time":0.2119816249,"remaining_time":0.2278142774},
{"learn":[0.2634246498],"iteration":482,"passed_time":0.2125326826,"remaining_time":0.2274935753},
{"learn":[0.2632611172],"iteration":483,"passed_time":0.213003369,"remaining_time":0.2270862363},
{"learn":[0.2629666226],"iteration":484,"passed_time":0.2134060585,"remaining_time":0.2266064333},
{"learn":[0.2628883485],"iteration":485,"passed_time":0.2138346219,"remaining_time":0.2261543121},
{"learn":[0.2626150613],"iteration":486,"passed_time":0.2142571856,"remaining_time":0.2256959675},
{"learn":[0.2621979062],"iteration":487,"passed_time":0.2146864989,"remaining_time":0.2252448513},
{"learn":[0.2620620098],"iteration":488,"passed_time":0.2151120624,"remaining_time":0.2247899057},
{"learn":[0.2620248984],"iteration":489,"passed_time":0.2155130854,"remaining_time":0.2243095379},
{"learn":[0.2619715418],"iteration":490,"passed_time":0.215930191,"remaining_time":0.2238461654},
{"learn":[0.2616562395],"iteration":491,"passed_time":0.2163294224,"remaining_time":0.2233645255},
{"learn":[0.2614860046],"iteration":492,"passed_time":0.2167132795,"remaining_time":0.2228674091},
{"learn":[0.261274435],"iteration":493,"passed_time":0.2171289685,"remaining_time":0.2224033563},
{"learn":[0.2611082336],"iteration":494,"passed_time":0.2175440741,"remaining_time":0.2219389039},
{"learn":[0.260841365],"iteration":495,"passed_time":0.2179410973,"remaining_time":0.2214562763},
{"learn":[0.2606076384],"iteration":496,"passed_time":0.2183841183,"remaining_time":0.2210205463},
{"learn":[0.2603988321],"iteration":497,"passed_time":0.218806432,"remaining_time":0.2205639134},
{"learn":[0.2603533193],"iteration":498,"passed_time":0.2192457032,"remaining_time":0.2201244435},
{"learn":[0.260144271],"iteration":499,"passed_time":0.2196486427,"remaining_time":0.2196486427},
{"learn":[0.2599335336],"iteration":500,"passed_time":0.2201929091,"remaining_time":0.2193138954},
{"learn":[0.2597931495],"iteration":501,"passed_time":0.2206488878,"remaining_time":0.2188907293},
{"learn":[0.2597309431],"iteration":502,"passed_time":0.2210437444,"remaining_time":0.2184070397},
{"learn":[0.2596610395],"iteration":503,"passed_time":0.2215094727,"remaining_time":0.2179934493},
{"learn":[0.2594519784],"iteration":504,"passed_time":0.2218878301,"remaining_time":0.2174940117},
{"learn":[0.2593339269],"iteration":505,"passed_time":0.2222605211,"remaining_time":0.2169895206},
{"learn":[0.2590963715],"iteration":506,"passed_time":0.2226932509,"remaining_time":0.2165439304},
{"learn":[0.2588078966],"iteration":507,"passed_time":0.2231144813,"remaining_time":0.2160872535},
{"learn":[0.2586388642],"iteration":508,"passed_time":0.2234992967,"remaining_time":0.2155955888},
{"learn":[0.2584601107],"iteration":509,"passed_time":0.2239123608,"remaining_time":0.2151314839},
{"learn":[0.2583516057],"iteration":510,"passed_time":0.2243289247,"remaining_time":0.214670928},
{"learn":[0.2580908354],"iteration":511,"passed_time":0.224701324,"remaining_time":0.2141684495},
{"learn":[0.2578602515],"iteration":512,"passed_time":0.2251480116,"remaining_time":0.2137370012},
{"learn":[0.2578385309],"iteration":513,"passed_time":0.2253858338,"remaining_time":0.2131080063},
{"learn":[0.2576413875],"iteration":514,"passed_time":0.2258122723,"remaining_time":0.2126581593},
{"learn":[0.2575540599],"iteration":515,"passed_time":0.2262057956,"remaining_time":0.2121775292},
{"learn":[0.2574862247],"iteration":516,"passed_time":0.2266089435,"remaining_time":0.2117062277},
{"learn":[0.2572988297],"iteration":517,"passed_time":0.227027549,"remaining_time":0.2112495726},
{"learn":[0.2570199798],"iteration":518,"passed_time":0.227429072,"remaining_time":0.2107772324},
{"learn":[0.2566525304],"iteration":519,"passed_time":0.2279875043,"remaining_time":0.2104500039},
{"learn":[0.2565015486],"iteration":520,"passed_time":0.2283661533,"remaining_time":0.2099565978},
{"learn":[0.2563414973],"iteration":521,"passed_time":0.2287556352,"remaining_time":0.209473551},
{"learn":[0.2561255619],"iteration":522,"passed_time":0.2292354045,"remaining_time":0.2090732083},
{"learn":[0.2560233831],"iteration":523,"passed_time":0.2296088454,"remaining_time":0.2085759741},
{"learn":[0.2558370589],"iteration":524,"passed_time":0.2299817447,"remaining_time":0.2080787214},
{"learn":[0.2555813474],"iteration":525,"passed_time":0.23036881,"remaining_time":0.2075947071},
{"learn":[0.2553377799],"iteration":526,"passed_time":0.2307781659,"remaining_time":0.2071310673},
{"learn":[0.2552046341],"iteration":527,"passed_time":0.23122677,"remaining_time":0.2067027187},
{"learn":[0.2550323514],"iteration":528,"passed_time":0.2316750408,"remaining_time":0.2062739967},
{"learn":[0.2549315457],"iteration":529,"passed_time":0.2321023543,"remaining_time":0.205826616},
{"learn":[0.2547328147],"iteration":530,"passed_time":0.2325319592,"remaining_time":0.205381335},
{"learn":[0.2544100636],"iteration":531,"passed_time":0.2329659807,"remaining_time":0.204939998},
{"learn":[0.2543428566],"iteration":532,"passed_time":0.2333910026,"remaining_time":0.2044908034},
{"learn":[0.2541401276],"iteration":533,"passed_time":0.2337674017,"remaining_time":0.2039992681},
{"learn":[0.2539564762],"iteration":534,"passed_time":0.2341597584,"remaining_time":0.203522033},
{"learn":[0.2536723429],"iteration":535,"passed_time":0.2346823591,"remaining_time":0.2031578631},
{"learn":[0.2534073169],"iteration":536,"passed_time":0.2350964231,"remaining_time":0.2026995231},
{"learn":[0.2531900745],"iteration":537,"passed_time":0.2355029042,"remaining_time":0.2022348359},
{"learn":[0.2531347206],"iteration":538,"passed_time":0.2359182182,"remaining_time":0.2017779194},
{"learn":[0.2529195138],"iteration":539,"passed_time":0.2363457816,"remaining_time":0.2013315917},
{"learn":[0.2528576473],"iteration":540,"passed_time":0.2367530543,"remaining_time":0.2008681181},
{"learn":[0.2527129875],"iteration":541,"passed_time":0.2372211991,"remaining_time":0.20045629},
{"learn":[0.2526128005],"iteration":542,"passed_time":0.2376383464,"remaining_time":0.2000013339},
{"learn":[0.252406061],"iteration":543,"passed_time":0.2381545723,"remaining_time":0.199629568},
{"learn":[0.2522080253],"iteration":544,"passed_time":0.2385343463,"remaining_time":0.1991433533},
{"learn":[0.2521558177],"iteration":545,"passed_time":0.2388739971,"remaining_time":0.1986241661},
{"learn":[0.2521267876],"iteration":546,"passed_time":0.2392599792,"remaining_time":0.1981440047},
{"learn":[0.2519278987],"iteration":547,"passed_time":0.2396620021,"remaining_time":0.1976774178},
{"learn":[0.2516894255],"iteration":548,"passed_time":0.2400815242,"remaining_time":0.1972254416},
{"learn":[0.2515625496],"iteration":549,"passed_time":0.2404884636,"remaining_time":0.1967632884},
{"learn":[0.2513037552],"iteration":550,"passed_time":0.2409641081,"remaining_time":0.1963573222},
{"learn":[0.2511493963],"iteration":551,"passed_time":0.241402171,"remaining_time":0.1959206026},
{"learn":[0.251021477],"iteration":552,"passed_time":0.2418211515,"remaining_time":0.1954684534},
{"learn":[0.2509225608],"iteration":553,"passed_time":0.2422609227,"remaining_time":0.1950331616},
{"learn":[0.250804807],"iteration":554,"passed_time":0.242682528,"remaining_time":0.1945832883},
{"learn":[0.2505856925],"iteration":555,"passed_time":0.2430737182,"remaining_time":0.1941092282},
{"learn":[0.2504514487],"iteration":556,"passed_time":0.2434864489,"remaining_time":0.1936525976},
{"learn":[0.2503354346],"iteration":557,"passed_time":0.2439053877,"remaining_time":0.1932010419},
{"learn":[0.2501139965],"iteration":558,"passed_time":0.2443018693,"remaining_time":0.1927318861},
{"learn":[0.250049293],"iteration":559,"passed_time":0.244687143,"remaining_time":0.1922541838},
{"learn":[0.249869038],"iteration":560,"passed_time":0.2452067438,"remaining_time":0.1918819261},
{"learn":[0.2496161758],"iteration":561,"passed_time":0.2455835596,"remaining_time":0.1913978632},
{"learn":[0.2493832506],"iteration":562,"passed_time":0.2461793235,"remaining_time":0.1910841285},
{"learn":[0.2492732911],"iteration":563,"passed_time":0.2465708052,"remaining_time":0.1906114736},
{"learn":[0.2492014786],"iteration":564,"passed_time":0.2471275293,"remaining_time":0.1902663279},
{"learn":[0.249063859],"iteration":565,"passed_time":0.2475355103,"remaining_time":0.1898063807},
{"learn":[0.2490362805],"iteration":566,"passed_time":0.2478169139,"remaining_time":0.1892499536},
{"learn":[0.2488869697],"iteration":567,"passed_time":0.2483130158,"remaining_time":0.1888577866},
{"learn":[0.2486689562],"iteration":568,"passed_time":0.2487563284,"remaining_time":0.1884252681},
{"learn":[0.2485658319],"iteration":569,"passed_time":0.2492700545,"remaining_time":0.1880458306},
{"learn":[0.2484023586],"iteration":570,"passed_time":0.249703576,"remaining_time":0.1876056639},
{"learn":[0.2482679776],"iteration":571,"passed_time":0.250088933,"remaining_time":0.1871294814},
{"learn":[0.2480620476],"iteration":572,"passed_time":0.2504757067,"remaining_time":0.1866546715},
{"learn":[0.2478949785],"iteration":573,"passed_time":0.2508526891,"remaining_time":0.1861729017},
{"learn":[0.2477490045],"iteration":574,"passed_time":0.2512190887,"remaining_time":0.1856836743},
{"learn":[0.2474959513],"iteration":575,"passed_time":0.2515996543,"remaining_time":0.1852053011},
{"learn":[0.2473708249],"iteration":576,"passed_time":0.2520177182,"remaining_time":0.184754757},
{"learn":[0.2470976407],"iteration":577,"passed_time":0.2523912424,"remaining_time":0.1842718068},
{"learn":[0.2467883632],"iteration":578,"passed_time":0.2528095563,"remaining_time":0.1838218017},
{"learn":[0.2465507822],"iteration":579,"passed_time":0.2532268285,"remaining_time":0.1833711517},
{"learn":[0.2464174016],"iteration":580,"passed_time":0.2536556419,"remaining_time":0.1829289397},
{"learn":[0.246195538],"iteration":581,"passed_time":0.2540555816,"remaining_time":0.1824660362},
{"learn":[0.2460058831],"iteration":582,"passed_time":0.2544900197,"remaining_time":0.1820280244},
{"learn":[0.2459054776],"iteration":583,"passed_time":0.2549134166,"remaining_time":0.1815821598},
{"learn":[0.2457346325],"iteration":584,"passed_time":0.2553691037,"remaining_time":0.1811592787},
{"learn":[0.2455591214],"iteration":585,"passed_time":0.255756544,"remaining_time":0.1806880703},
{"learn":[0.2455177783],"iteration":586,"passed_time":0.256113444,"remaining_time":0.1801956599},
{"learn":[0.2454092512],"iteration":587,"passed_time":0.256544424,"remaining_time":0.1797556168},
{"learn":[0.2452060223],"iteration":588,"passed_time":0.256973654,"remaining_time":0.1793143833},
{"learn":[0.2451097601],"iteration":589,"passed_time":0.2574113836,"remaining_time":0.1788790971},
{"learn":[0.245002802],"iteration":590,"passed_time":0.2578444467,"remaining_time":0.1784405731},
{"learn":[0.2448599718],"iteration":591,"passed_time":0.2582668437,"remaining_time":0.1779947166},
{"learn":[0.2447508719],"iteration":592,"passed_time":0.2586554923,"remaining_time":0.1775257763},
{"learn":[0.244567081],"iteration":593,"passed_time":0.2590361412,"remaining_time":0.1770516386},
{"learn":[0.2444722342],"iteration":594,"passed_time":0.25945558,"remaining_time":0.1766042183},
{"learn":[0.2442949677],"iteration":595,"passed_time":0.2598706023,"remaining_time":0.1761538982},
{"learn":[0.2440963854],"iteration":596,"passed_time":0.260270542,"remaining_time":0.175693515},
{"learn":[0.2440412092],"iteration":597,"passed_time":0.2606754815,"remaining_time":0.1752366949},
{"learn":[0.2438776987],"iteration":598,"passed_time":0.2611618755,"remaining_time":0.1748345778},
{"learn":[0.2436218384],"iteration":599,"passed_time":0.2616857261,"remaining_time":0.1744571507},
{"learn":[0.2434900821],"iteration":600,"passed_time":0.2621410382,"remaining_time":0.1740337342},
{"learn":[0.2432191904],"iteration":601,"passed_time":0.2625630603,"remaining_time":0.1735882026},
{"learn":[0.2430185381],"iteration":602,"passed_time":0.2630208723,"remaining_time":0.1731663122},
{"learn":[0.2428032404],"iteration":603,"passed_time":0.2634456025,"remaining_time":0.1727226135},
{"learn":[0.2425424579],"iteration":604,"passed_time":0.2638657912,"remaining_time":0.1722760125},
{"learn":[0.2423815876],"iteration":605,"passed_time":0.2642951046,"remaining_time":0.171835431},
{"learn":[0.2421613704],"iteration":606,"passed_time":0.2650109879,"remaining_time":0.1715804254},
{"learn":[0.2419464798],"iteration":607,"passed_time":0.2657467453,"remaining_time":0.1713367173},
{"learn":[0.2418141655],"iteration":608,"passed_time":0.2661638925,"remaining_time":0.1708868341},
{"learn":[0.2416383337],"iteration":609,"passed_time":0.2665883311,"remaining_time":0.1704417199},
{"learn":[0.2415682051],"iteration":610,"passed_time":0.2670286439,"remaining_time":0.1700067798},
{"learn":[0.241476248],"iteration":611,"passed_time":0.2674809145,"remaining_time":0.1695794033},
{"learn":[0.2413754281],"iteration":612,"passed_time":0.2677881502,"remaining_time":0.1690603819},
{"learn":[0.2411771028],"iteration":613,"passed_time":0.2681997977,"remaining_time":0.1686076904},
{"learn":[0.2410644164],"iteration":614,"passed_time":0.2685716137,"remaining_time":0.1681301972},
{"learn":[0.2407061783],"iteration":615,"passed_time":0.2690697571,"remaining_time":0.1677317967},
{"learn":[0.2406044273],"iteration":616,"passed_time":0.2695309023,"remaining_time":0.1673101063},
{"learn":[0.2404073028],"iteration":617,"passed_time":0.2699121762,"remaining_time":0.166838918},
{"learn":[0.2401104178],"iteration":618,"passed_time":0.270481983,"remaining_time":0.1664840639},
{"learn":[0.2400361838],"iteration":619,"passed_time":0.270932712,"remaining_time":0.1660555332},
{"learn":[0.2398150677],"iteration":620,"passed_time":0.2713445262,"remaining_time":0.165603181},
{"learn":[0.2395772701],"iteration":621,"passed_time":0.2717583819,"remaining_time":0.1651521999},
{"learn":[0.2394531216],"iteration":622,"passed_time":0.2721768624,"remaining_time":0.1647041366},
{"learn":[0.2394175559],"iteration":623,"passed_time":0.2725825102,"remaining_time":0.1642484356},
{"learn":[0.2393080632],"iteration":624,"passed_time":0.2730185732,"remaining_time":0.1638111439},
{"learn":[0.2389447199],"iteration":625,"passed_time":0.2734252209,"remaining_time":0.1633562821},
{"learn":[0.2388612177],"iteration":626,"passed_time":0.2739183229,"remaining_time":0.1629530055},
{"learn":[0.2387998803],"iteration":627,"passed_time":0.2744546313,"remaining_time":0.1625750364},
{"learn":[0.2386864073],"iteration":628,"passed_time":0.2748780282,"remaining_time":0.1621299658},
{"learn":[0.2385643938],"iteration":629,"passed_time":0.2754282943,"remaining_time":0.1617594744},
{"learn":[0.2384053594],"iteration":630,"passed_time":0.2759373122,"remaining_time":0.1613642919},
{"learn":[0.2381900225],"iteration":631,"passed_time":0.2763894578,"remaining_time":0.1609356337},
{"learn":[0.2380327362],"iteration":632,"passed_time":0.2770788424,"remaining_time":0.1606444473},
{"learn":[0.2378440682],"iteration":633,"passed_time":0.2775661947,"remaining_time":0.1602353742},
{"learn":[0.2375492778],"iteration":634,"passed_time":0.2780438391,"remaining_time":0.1598204744},
{"learn":[0.2373735748],"iteration":635,"passed_time":0.2784498618,"remaining_time":0.1593643863},
{"learn":[0.2371928273],"iteration":636,"passed_time":0.2788393437,"remaining_time":0.1588990295},
{"learn":[0.2368907841],"iteration":637,"passed_time":0.2792448248,"remaining_time":0.1584429884},
{"learn":[0.2367077442],"iteration":638,"passed_time":0.2797573843,"remaining_time":0.1580475989},
{"learn":[0.2366029773],"iteration":639,"passed_time":0.2802009886,"remaining_time":0.1576130561},
{"learn":[0.2364903772],"iteration":640,"passed_time":0.2806217607,"remaining_time":0.1571656975},
{"learn":[0.2362135689],"iteration":641,"passed_time":0.2810621151,"remaining_time":0.1567293415},
{"learn":[0.2359853163],"iteration":642,"passed_time":0.2814694712,"remaining_time":0.156274652},
{"learn":[0.2357204871],"iteration":643,"passed_time":0.281916867,"remaining_time":0.1558422432},
{"learn":[0.2354646252],"iteration":644,"passed_time":0.2823275979,"remaining_time":0.1553896081},
{"learn":[0.2352768207],"iteration":645,"passed_time":0.2827295791,"remaining_time":0.1549323081},
{"learn":[0.2351607092],"iteration":646,"passed_time":0.2831266856,"remaining_time":0.1544725194},
{"learn":[0.2349055034],"iteration":647,"passed_time":0.2835549157,"remaining_time":0.1540298307},
{"learn":[0.2348318083],"iteration":648,"passed_time":0.283956647,"remaining_time":0.1535728553},
{"learn":[0.2347679993],"iteration":649,"passed_time":0.284364753,"remaining_time":0.1531194824},
{"learn":[0.2346510579],"iteration":650,"passed_time":0.2847997744,"remaining_time":0.1526806778},
{"learn":[0.2344591154],"iteration":651,"passed_time":0.2853262915,"remaining_time":0.15229072},
{"learn":[0.2343290816],"iteration":652,"passed_time":0.285795103,"remaining_time":0.1518696795},
{"learn":[0.234090679],"iteration":653,"passed_time":0.2862194999,"remaining_time":0.1514249954},
{"learn":[0.2339268321],"iteration":654,"passed_time":0.2866988942,"remaining_time":0.1510093412},
{"learn":[0.2337521096],"iteration":655,"passed_time":0.2871053753,"remaining_time":0.1505552578},
{"learn":[0.2335020154],"iteration":656,"passed_time":0.2874960238,"remaining_time":0.1500930535},
{"learn":[0.2332901728],"iteration":657,"passed_time":0.2879492526,"remaining_time":0.1496635933},
{"learn":[0.233213567],"iteration":658,"passed_time":0.2885130597,"remaining_time":0.1492912798},
{"learn":[0.2330818901],"iteration":659,"passed_time":0.2889087079,"remaining_time":0.1488317586},
{"learn":[0.2328114031],"iteration":660,"passed_time":0.2893396879,"remaining_time":0.148390551},
{"learn":[0.2326801641],"iteration":661,"passed_time":0.2898137075,"remaining_time":0.1479713491},
{"learn":[0.2324252195],"iteration":662,"passed_time":0.2902065225,"remaining_time":0.147510706},
{"learn":[0.2322998151],"iteration":663,"passed_time":0.2907140405,"remaining_time":0.1471083097},
{"learn":[0.2322530971],"iteration":664,"passed_time":0.2910855232,"remaining_time":0.1466370681},
{"learn":[0.2319449425],"iteration":665,"passed_time":0.2915245444,"remaining_time":0.1461999968},
{"learn":[0.2317787629],"iteration":666,"passed_time":0.2919801065,"remaining_time":0.1457711776},
{"learn":[0.2316609859],"iteration":667,"passed_time":0.2924180028,"remaining_time":0.1453334984},
{"learn":[0.2315479342],"iteration":668,"passed_time":0.2928435246,"remaining_time":0.1448896961},
{"learn":[0.2313991254],"iteration":669,"passed_time":0.293415873,"remaining_time":0.1445182658},
{"learn":[0.2312309872],"iteration":670,"passed_time":0.2938387283,"remaining_time":0.1440729383},
{"learn":[0.2311456748],"iteration":671,"passed_time":0.294344663,"remaining_time":0.1436682284},
{"learn":[0.2310449905],"iteration":672,"passed_time":0.2947718931,"remaining_time":0.1432249763},
{"learn":[0.2308418249],"iteration":673,"passed_time":0.295176291,"remaining_time":0.1427707283},
{"learn":[0.2307379586],"iteration":674,"passed_time":0.2956087292,"remaining_time":0.1423301289},
{"learn":[0.2306175295],"iteration":675,"passed_time":0.2960869569,"remaining_time":0.1419115},
{"learn":[0.2304752945],"iteration":676,"passed_time":0.2964848967,"remaining_time":0.1414543894},
{"learn":[0.2304275819],"iteration":677,"passed_time":0.2970159553,"remaining_time":0.1410606749},
{"learn":[0.2300508719],"iteration":678,"passed_time":0.2976171773,"remaining_time":0.1406997259},
{"learn":[0.2299268131],"iteration":679,"passed_time":0.2981772762,"remaining_time":0.1403187182},
{"learn":[0.2297302003],"iteration":680,"passed_time":0.2987368751,"remaining_time":0.1399369503},
{"learn":[0.2294960253],"iteration":681,"passed_time":0.2992245607,"remaining_time":0.1395211295},
{"learn":[0.2293456186],"iteration":682,"passed_time":0.2998617394,"remaining_time":0.1391744823},
{"learn":[0.2290552549],"iteration":683,"passed_time":0.3003517999,"remaining_time":0.1387590187},
{"learn":[0.2289392377],"iteration":684,"passed_time":0.3008800669,"remaining_time":0.1383609067},
{"learn":[0.2287272266],"iteration":685,"passed_time":0.3013454203,"remaining_time":0.137933618},
{"learn":[0.2284743056],"iteration":686,"passed_time":0.3018111902,"remaining_time":0.1375064084},
{"learn":[0.228298822],"iteration":687,"passed_time":0.3022505864,"remaining_time":0.1370671264},
{"learn":[0.2280624309],"iteration":688,"passed_time":0.30263986,"remaining_time":0.1366052198},
{"learn":[0.2278030408],"iteration":689,"passed_time":0.3032341239,"remaining_time":0.1362356209},
{"learn":[0.2276535251],"iteration":690,"passed_time":0.3037020188,"remaining_time":0.1358088622},
{"learn":[0.2273382072],"iteration":691,"passed_time":0.3040963754,"remaining_time":0.1353492538},
{"learn":[0.2271595613],"iteration":692,"passed_time":0.3046324755,"remaining_time":0.1349526262},
{"learn":[0.2270934095],"iteration":693,"passed_time":0.305208157,"remaining_time":0.134573049},
{"learn":[0.226887371],"iteration":694,"passed_time":0.3055738066,"remaining_time":0.1341007353},
{"learn":[0.2268099695],"iteration":695,"passed_time":0.3060414515,"remaining_time":0.1336732777},
{"learn":[0.2266978694],"iteration":696,"passed_time":0.3064580571,"remaining_time":0.1332235169},
{"learn":[0.2265577444],"iteration":697,"passed_time":0.3068907036,"remaining_time":0.1327807915},
{"learn":[0.2263057945],"iteration":698,"passed_time":0.3072580615,"remaining_time":0.1323099807},
{"learn":[0.2262012869],"iteration":699,"passed_time":0.3076650842,"remaining_time":0.1318564647},
{"learn":[0.226149525],"iteration":700,"passed_time":0.3080592742,"remaining_time":0.1313976077},
{"learn":[0.2259821833],"iteration":701,"passed_time":0.3085141696,"remaining_time":0.1309647045},
{"learn":[0.2258862118],"iteration":702,"passed_time":0.3089737732,"remaining_time":0.1305337278},
{"learn":[0.2257702095],"iteration":703,"passed_time":0.3095268308,"remaining_time":0.1301419629},
{"learn":[0.2256841374],"iteration":704,"passed_time":0.3099528943,"remaining_time":0.1296966012},
{"learn":[0.2255829403],"iteration":705,"passed_time":0.3103483342,"remaining_time":0.1292385414},
{"learn":[0.2255050313],"iteration":706,"passed_time":0.3107085674,"remaining_time":0.1287660682},
{"learn":[0.2251032304],"iteration":707,"passed_time":0.3111320477,"remaining_time":0.1283199971},
{"learn":[0.2250147864],"iteration":708,"passed_time":0.3116208582,"remaining_time":0.1279008036},
{"learn":[0.2248544252],"iteration":709,"passed_time":0.3120065486,"remaining_time":0.1274392945},
{"learn":[0.2247857583],"iteration":710,"passed_time":0.3124582776,"remaining_time":0.1270048414},
{"learn":[0.2245622603],"iteration":711,"passed_time":0.312899632,"remaining_time":0.1265661433},
{"learn":[0.2244087361],"iteration":712,"passed_time":0.3133154876,"remaining_time":0.1261171738},
{"learn":[0.224331807],"iteration":713,"passed_time":0.3137179272,"remaining_time":0.1256629232},
{"learn":[0.2242812517],"iteration":714,"passed_time":0.3141265332,"remaining_time":0.1252112755},
{"learn":[0.2240108355],"iteration":715,"passed_time":0.3145278062,"remaining_time":0.1247568393},
{"learn":[0.2238398609],"iteration":716,"passed_time":0.3149845765,"remaining_time":0.1243244563},
{"learn":[0.2237005924],"iteration":717,"passed_time":0.3154626376,"remaining_time":0.1239003674},
{"learn":[0.2235536958],"iteration":718,"passed_time":0.3158853679,"remaining_time":0.123454504},
{"learn":[0.2235108461],"iteration":719,"passed_time":0.3163478464,"remaining_time":0.1230241625},
{"learn":[0.2234507688],"iteration":720,"passed_time":0.3167727016,"remaining_time":0.122579173},
{"learn":[0.2234480192],"iteration":721,"passed_time":0.3169891915,"remaining_time":0.12205401},
{"learn":[0.2232869993],"iteration":722,"passed_time":0.3175635397,"remaining_time":0.1216668057},
{"learn":[0.2230719197],"iteration":723,"passed_time":0.3180314346,"remaining_time":0.1212385027},
{"learn":[0.2229142667],"iteration":724,"passed_time":0.3184184166,"remaining_time":0.1207793994},
{"learn":[0.2227631677],"iteration":725,"passed_time":0.3189127686,"remaining_time":0.1203610173},
{"learn":[0.2226386821],"iteration":726,"passed_time":0.3200356329,"remaining_time":0.1201784426},
{"learn":[0.2225407462],"iteration":727,"passed_time":0.3204947782,"remaining_time":0.1197453017},
{"learn":[0.2223586464],"iteration":728,"passed_time":0.3208909264,"remaining_time":0.1192886709},
{"learn":[0.2222525909],"iteration":729,"passed_time":0.3213072403,"remaining_time":0.1188396642},
{"learn":[0.2221638396],"iteration":730,"passed_time":0.3217020136,"remaining_time":0.1183828203},
{"learn":[0.2220068106],"iteration":731,"passed_time":0.3220759962,"remaining_time":0.1179185341},
{"learn":[0.2219506323],"iteration":732,"passed_time":0.3225139758,"remaining_time":0.1174778056},
{"learn":[0.2217405684],"iteration":733,"passed_time":0.3230275769,"remaining_time":0.1170644897},
{"learn":[0.2214901604],"iteration":734,"passed_time":0.3234193503,"remaining_time":0.1166069766},
{"learn":[0.2213978673],"iteration":735,"passed_time":0.3238468304,"remaining_time":0.11616245},
{"learn":[0.221322103],"iteration":736,"passed_time":0.3242293542,"remaining_time":0.1157019269},
{"learn":[0.2211884423],"iteration":737,"passed_time":0.3247015822,"remaining_time":0.1152734614},
{"learn":[0.2211123373],"iteration":738,"passed_time":0.3250961055,"remaining_time":0.1148174337},
{"learn":[0.221042623],"iteration":739,"passed_time":0.3254983784,"remaining_time":0.1143642951},
{"learn":[0.2209252844],"iteration":740,"passed_time":0.3259498574,"remaining_time":0.1139284927},
{"learn":[0.2208825391],"iteration":741,"passed_time":0.326344464,"remaining_time":0.1134728729},
{"learn":[0.2205911782],"iteration":742,"passed_time":0.3268771059,"remaining_time":0.1130651631},
{"learn":[0.2202934218],"iteration":743,"passed_time":0.3273272099,"remaining_time":0.1126287174},
{"learn":[0.2200853261],"iteration":744,"passed_time":0.3277383157,"remaining_time":0.1121788866},
{"learn":[0.2199944327],"iteration":745,"passed_time":0.3283585369,"remaining_time":0.1118003597},
{"learn":[0.2198903986],"iteration":746,"passed_time":0.328749852,"remaining_time":0.111343658},
{"learn":[0.2198129131],"iteration":747,"passed_time":0.3291342507,"remaining_time":0.110884801},
{"learn":[0.2197568874],"iteration":748,"passed_time":0.329529899,"remaining_time":0.1104299127},
{"learn":[0.2196780403],"iteration":749,"passed_time":0.329950546,"remaining_time":0.1099835153},
{"learn":[0.2195640048],"iteration":750,"passed_time":0.3303890673,"remaining_time":0.1095431128},
{"learn":[0.2193127538],"iteration":751,"passed_time":0.3309371251,"remaining_time":0.1091388391},
{"learn":[0.2191878905],"iteration":752,"passed_time":0.3313283985,"remaining_time":0.1086827549},
{"learn":[0.2189300909],"iteration":753,"passed_time":0.3319839096,"remaining_time":0.1083130527},
{"learn":[0.2188907816],"iteration":754,"passed_time":0.3324692204,"remaining_time":0.1078873629},
{"learn":[0.2186476424],"iteration":755,"passed_time":0.3329968208,"remaining_time":0.1074751644},
{"learn":[0.2184793103],"iteration":756,"passed_time":0.3333762614,"remaining_time":0.1070151011},
{"learn":[0.2184640981],"iteration":757,"passed_time":0.3338974038,"remaining_time":0.1066004904},
{"learn":[0.2182125524],"iteration":758,"passed_time":0.3343175926,"remaining_time":0.1061535439},
{"learn":[0.2180182393],"iteration":759,"passed_time":0.3347690716,"remaining_time":0.1057165489},
{"learn":[0.217802373],"iteration":760,"passed_time":0.3351496788,"remaining_time":0.1052572579},
{"learn":[0.2177208554],"iteration":761,"passed_time":0.3357249437,"remaining_time":0.1048589719},
{"learn":[0.2176677976],"iteration":762,"passed_time":0.3361597151,"remaining_time":0.1044165825},
{"learn":[0.2174746989],"iteration":763,"passed_time":0.3365756957,"remaining_time":0.1039684086},
{"learn":[0.2174288899],"iteration":764,"passed_time":0.337005634,"remaining_time":0.1035246065},
{"learn":[0.2171758011],"iteration":765,"passed_time":0.3374580713,"remaining_time":0.1030877137},
{"learn":[0.2170501471],"iteration":766,"passed_time":0.3378930094,"remaining_time":0.1026454644},
{"learn":[0.2168445368],"iteration":767,"passed_time":0.3383288641,"remaining_time":0.102203511},
{"learn":[0.2165038687],"iteration":768,"passed_time":0.338702305,"remaining_time":0.101742825},
{"learn":[0.2164584179],"iteration":769,"passed_time":0.3391366598,"remaining_time":0.1013005607},
{"learn":[0.2164074023],"iteration":770,"passed_time":0.3395416826,"remaining_time":0.1008496048},
{"learn":[0.2162345635],"iteration":771,"passed_time":0.3401461127,"remaining_time":0.1004576602},
{"learn":[0.216087576],"iteration":772,"passed_time":0.340556427,"remaining_time":0.1000081616},
{"learn":[0.215957775],"iteration":773,"passed_time":0.3409804072,"remaining_time":0.09956275456},
{"learn":[0.2158780911],"iteration":774,"passed_time":0.3413730139,"remaining_time":0.09910829436},
{"learn":[0.2156609025],"iteration":775,"passed_time":0.3419096139,"remaining_time":0.09869555866},
{"learn":[0.2155938721],"iteration":776,"passed_time":0.3423214281,"remaining_time":0.09824669042},
{"learn":[0.2154044147],"iteration":777,"passed_time":0.3427021603,"remaining_time":0.09778904832},
{"learn":[0.215136461],"iteration":778,"passed_time":0.3431652221,"remaining_time":0.09735496031},
{"learn":[0.2150478273],"iteration":779,"passed_time":0.3435828276,"remaining_time":0.09690797703},
{"learn":[0.2148128863],"iteration":780,"passed_time":0.3439943501,"remaining_time":0.09645936323},
{"learn":[0.2146581839],"iteration":781,"passed_time":0.3444719529,"remaining_time":0.09602926564},
{"learn":[0.2145236942],"iteration":782,"passed_time":0.344855185,"remaining_time":0.09557289291},
{"learn":[0.2142271709],"iteration":783,"passed_time":0.3452521665,"remaining_time":0.09512049486},
{"learn":[0.2142027023],"iteration":784,"passed_time":0.3456532312,"remaining_time":0.09466935631},
{"learn":[0.2141294406],"iteration":785,"passed_time":0.3461021269,"remaining_time":0.0942313679},
{"learn":[0.214009768],"iteration":786,"passed_time":0.3465499394,"remaining_time":0.09379305857},
{"learn":[0.2139304241],"iteration":787,"passed_time":0.3469427545,"remaining_time":0.09333992886},
{"learn":[0.2138764591],"iteration":788,"passed_time":0.3473603183,"remaining_time":0.09289357056},
{"learn":[0.2137049964],"iteration":789,"passed_time":0.3478840439,"remaining_time":0.09247550535},
{"learn":[0.2136111117],"iteration":790,"passed_time":0.3483715629,"remaining_time":0.09204760638},
{"learn":[0.2134780943],"iteration":791,"passed_time":0.3488126257,"remaining_time":0.09160735624},
{"learn":[0.2132251013],"iteration":792,"passed_time":0.3492695211,"remaining_time":0.0911712369},
{"learn":[0.2129545997],"iteration":793,"passed_time":0.349772706,"remaining_time":0.09074707484},
{"learn":[0.2128921135],"iteration":794,"passed_time":0.3502491421,"remaining_time":0.09031581651},
{"learn":[0.2126776969],"iteration":795,"passed_time":0.3511863484,"remaining_time":0.09000253151},
{"learn":[0.2125057793],"iteration":796,"passed_time":0.3516705342,"remaining_time":0.08957229416},
{"learn":[0.2124542091],"iteration":797,"passed_time":0.3521814271,"remaining_time":0.08914868204},
{"learn":[0.2123573934],"iteration":798,"passed_time":0.3525517848,"remaining_time":0.08868949781},
{"learn":[0.2122634672],"iteration":799,"passed_time":0.3530433869,"remaining_time":0.08826084673},
{"learn":[0.2120482113],"iteration":800,"passed_time":0.3535083236,"remaining_time":0.08782541373},
{"learn":[0.2119128407],"iteration":801,"passed_time":0.3539554694,"remaining_time":0.0873855149},
{"learn":[0.2117890542],"iteration":802,"passed_time":0.3543714084,"remaining_time":0.08693794203},
{"learn":[0.2115589136],"iteration":803,"passed_time":0.3547870557,"remaining_time":0.08649037676},
{"learn":[0.2114781564],"iteration":804,"passed_time":0.3552161607,"remaining_time":0.08604615073},
{"learn":[0.2112793402],"iteration":805,"passed_time":0.3557033463,"remaining_time":0.08561594192},
{"learn":[0.2111674149],"iteration":806,"passed_time":0.3562062812,"remaining_time":0.08518935846},
{"learn":[0.2110744528],"iteration":807,"passed_time":0.3567298402,"remaining_time":0.08476748678},
{"learn":[0.2110663208],"iteration":808,"passed_time":0.3570110354,"remaining_time":0.0842881431},
{"learn":[0.2109794342],"iteration":809,"passed_time":0.3574427236,"remaining_time":0.0838445895},
{"learn":[0.2108729965],"iteration":810,"passed_time":0.3578564544,"remaining_time":0.08339688024},
{"learn":[0.2108521805],"iteration":811,"passed_time":0.3583756802,"remaining_time":0.08297367965},
{"learn":[0.2106545511],"iteration":812,"passed_time":0.3588377003,"remaining_time":0.08253708482},
{"learn":[0.2104508612],"iteration":813,"passed_time":0.3593393853,"remaining_time":0.08210949099},
{"learn":[0.2103585501],"iteration":814,"passed_time":0.3598715272,"remaining_time":0.08168862887},
{"learn":[0.2102372293],"iteration":815,"passed_time":0.36034813,"remaining_time":0.08125497048},
{"learn":[0.2100840361],"iteration":816,"passed_time":0.3607091548,"remaining_time":0.08079531864},
{"learn":[0.2099149205],"iteration":817,"passed_time":0.361120344,"remaining_time":0.0803470692},
{"learn":[0.2097887051],"iteration":818,"passed_time":0.3615157839,"remaining_time":0.07989542965},
{"learn":[0.2096000254],"iteration":819,"passed_time":0.3619190984,"remaining_time":0.07944565576},
{"learn":[0.2095843088],"iteration":820,"passed_time":0.362344662,"remaining_time":0.07900084591},
{"learn":[0.2095482887],"iteration":821,"passed_time":0.3627861414,"remaining_time":0.0785595294},
{"learn":[0.2093988862],"iteration":822,"passed_time":0.3631608739,"remaining_time":0.07810385746},
{"learn":[0.2091692295],"iteration":823,"passed_time":0.3635651884,"remaining_time":0.07765470044},
{"learn":[0.2088266274],"iteration":824,"passed_time":0.3639640449,"remaining_time":0.07720449436},
{"learn":[0.2087360402],"iteration":825,"passed_time":0.3643710259,"remaining_time":0.0767561241},
{"learn":[0.2085890075],"iteration":826,"passed_time":0.364827088,"remaining_time":0.07631812119},
{"learn":[0.2084233108],"iteration":827,"passed_time":0.3653009826,"remaining_time":0.07588377899},
{"learn":[0.2082980433],"iteration":828,"passed_time":0.3657132967,"remaining_time":0.07543663901},
{"learn":[0.2081563214],"iteration":829,"passed_time":0.3661872746,"remaining_time":0.07500221287},
{"learn":[0.2081112652],"iteration":830,"passed_time":0.3672399756,"remaining_time":0.07468538613},
{"learn":[0.2080162967],"iteration":831,"passed_time":0.3677514934,"remaining_time":0.07425751309},
{"learn":[0.2077530328],"iteration":832,"passed_time":0.368189723,"remaining_time":0.07381474639},
{"learn":[0.2076247657],"iteration":833,"passed_time":0.3686292025,"remaining_time":0.07337223935},
{"learn":[0.2074913323],"iteration":834,"passed_time":0.3690215176,"remaining_time":0.07292041964},
{"learn":[0.2073731333],"iteration":835,"passed_time":0.3694422063,"remaining_time":0.07247430842},
{"learn":[0.2071961908],"iteration":836,"passed_time":0.3699263088,"remaining_time":0.07204060732},
{"learn":[0.2070886633],"iteration":837,"passed_time":0.3703538305,"remaining_time":0.0715958479},
{"learn":[0.2067545916],"iteration":838,"passed_time":0.3708268918,"remaining_time":0.07115986839},
{"learn":[0.2066752904],"iteration":839,"passed_time":0.3713112443,"remaining_time":0.07072595129},
{"learn":[0.2064244032],"iteration":840,"passed_time":0.3718231787,"remaining_time":0.07029712892},
{"learn":[0.2062410345],"iteration":841,"passed_time":0.3722237017,"remaining_time":0.06984720294},
{"learn":[0.2061296792],"iteration":842,"passed_time":0.3726118087,"remaining_time":0.0693950818},
{"learn":[0.2060325765],"iteration":843,"passed_time":0.3731193267,"remaining_time":0.06896518361},
{"learn":[0.2059179626],"iteration":844,"passed_time":0.3736020959,"remaining_time":0.06853056196},
{"learn":[0.2057393522],"iteration":845,"passed_time":0.3740419087,"remaining_time":0.06808800702},
{"learn":[0.2056080261],"iteration":846,"passed_time":0.3745679675,"remaining_time":0.06766103782},
{"learn":[0.2054443404],"iteration":847,"passed_time":0.3751555652,"remaining_time":0.06724486545},
{"learn":[0.2053661079],"iteration":848,"passed_time":0.3755988778,"remaining_time":0.06680262727},
{"learn":[0.2053434135],"iteration":849,"passed_time":0.3761841839,"remaining_time":0.06638544422},
{"learn":[0.2052421512],"iteration":850,"passed_time":0.3766455791,"remaining_time":0.06594617072},
{"learn":[0.2050313203],"iteration":851,"passed_time":0.3771081409,"remaining_time":0.06550704794},
{"learn":[0.204863481],"iteration":852,"passed_time":0.3775092889,"remaining_time":0.06505728659},
{"learn":[0.2047632503],"iteration":853,"passed_time":0.3779149783,"remaining_time":0.06460841549},
{"learn":[0.2046973962],"iteration":854,"passed_time":0.3783467915,"remaining_time":0.06416407575},
{"learn":[0.2046725048],"iteration":855,"passed_time":0.3787555641,"remaining_time":0.06371588929},
{"learn":[0.2045235733],"iteration":856,"passed_time":0.3791478792,"remaining_time":0.06326504869},
{"learn":[0.2044010308],"iteration":857,"passed_time":0.3795537353,"remaining_time":0.06281658556},
{"learn":[0.2042750941],"iteration":858,"passed_time":0.3799669244,"remaining_time":0.0623694253},
{"learn":[0.2039847372],"iteration":859,"passed_time":0.380390613,"remaining_time":0.06192405327},
{"learn":[0.2038873256],"iteration":860,"passed_time":0.3808329674,"remaining_time":0.06148174502},
{"learn":[0.2038015447],"iteration":861,"passed_time":0.3812131996,"remaining_time":0.06102949136},
{"learn":[0.2037251296],"iteration":862,"passed_time":0.3816192641,"remaining_time":0.06058150542},
{"learn":[0.2037202642],"iteration":863,"passed_time":0.3818657109,"remaining_time":0.06010849153},
{"learn":[0.2036345237],"iteration":864,"passed_time":0.3822652756,"remaining_time":0.05965989851},
{"learn":[0.2036114636],"iteration":865,"passed_time":0.3828127085,"remaining_time":0.059234299},
{"learn":[0.2035866037],"iteration":866,"passed_time":0.3832248559,"remaining_time":0.05878766533},
{"learn":[0.2034053766],"iteration":867,"passed_time":0.3836219624,"remaining_time":0.05833882378},
{"learn":[0.2033678815],"iteration":868,"passed_time":0.3840932321,"remaining_time":0.05790128125},
{"learn":[0.2032352861],"iteration":869,"passed_time":0.3844720478,"remaining_time":0.05744984623},
{"learn":[0.2031474199],"iteration":870,"passed_time":0.3849321931,"remaining_time":0.05701062331},
{"learn":[0.2031303436],"iteration":871,"passed_time":0.3853790056,"remaining_time":0.05656939531},
{"learn":[0.2029943178],"iteration":872,"passed_time":0.3858373592,"remaining_time":0.05612983347},
{"learn":[0.2029704081],"iteration":873,"passed_time":0.3863060041,"remaining_time":0.05569171226},
{"learn":[0.2029140403],"iteration":874,"passed_time":0.3867748156,"remaining_time":0.05525354508},
{"learn":[0.2028705382],"iteration":875,"passed_time":0.3872104619,"remaining_time":0.05481061333},
{"learn":[0.202731446],"iteration":876,"passed_time":0.3877227297,"remaining_time":0.05437844442},
{"learn":[0.2025327495],"iteration":877,"passed_time":0.3881277525,"remaining_time":0.05393119113},
{"learn":[0.2025134642],"iteration":878,"passed_time":0.3885526911,"remaining_time":0.05348677545},
{"learn":[0.202322992],"iteration":879,"passed_time":0.3889840876,"remaining_time":0.05304328468},
{"learn":[0.2020553081],"iteration":880,"passed_time":0.3894014849,"remaining_time":0.05259793042},
{"learn":[0.201992332],"iteration":881,"passed_time":0.3898441309,"remaining_time":0.05215601751},
{"learn":[0.2017286709],"iteration":882,"passed_time":0.3902504453,"remaining_time":0.0517092889},
{"learn":[0.201550823],"iteration":883,"passed_time":0.390679467,"remaining_time":0.05126563141},
{"learn":[0.2013582635],"iteration":884,"passed_time":0.3911506534,"remaining_time":0.05082748603},
{"learn":[0.2011728349],"iteration":885,"passed_time":0.3915976742,"remaining_time":0.05038615673},
{"learn":[0.2010584753],"iteration":886,"passed_time":0.3920065718,"remaining_time":0.04993995785},
{"learn":[0.2009058143],"iteration":887,"passed_time":0.3924246357,"remaining_time":0.0494949991},
{"learn":[0.2006988204],"iteration":888,"passed_time":0.3928605737,"remaining_time":0.0490523326},
{"learn":[0.2006431012],"iteration":889,"passed_time":0.3932855123,"remaining_time":0.04860832174},
{"learn":[0.2005952262],"iteration":890,"passed_time":0.3936808272,"remaining_time":0.0481607297},
{"learn":[0.2004099255],"iteration":891,"passed_time":0.3940771837,"remaining_time":0.04771338099},
{"learn":[0.2002463974],"iteration":892,"passed_time":0.3945012056,"remaining_time":0.04726946137},
{"learn":[0.2001788406],"iteration":893,"passed_time":0.3948998537,"remaining_time":0.04682257773},
{"learn":[0.1999349293],"iteration":894,"passed_time":0.3952711698,"remaining_time":0.04637259533},
{"learn":[0.199755732],"iteration":895,"passed_time":0.3957048579,"remaining_time":0.04593002815},
{"learn":[0.1996171581],"iteration":896,"passed_time":0.396132088,"remaining_time":0.0454867392},
{"learn":[0.1994579771],"iteration":897,"passed_time":0.3966398143,"remaining_time":0.04505262924},
{"learn":[0.1994044588],"iteration":898,"passed_time":0.3970588365,"remaining_time":0.04460838986},
{"learn":[0.1993610238],"iteration":899,"passed_time":0.397520815,"remaining_time":0.04416897944},
{"learn":[0.1992432808],"iteration":900,"passed_time":0.3979185464,"remaining_time":0.0437224596},
{"learn":[0.1991813466],"iteration":901,"passed_time":0.3983464015,"remaining_time":0.04327932078},
{"learn":[0.1989335072],"iteration":902,"passed_time":0.3987336751,"remaining_time":0.04283185657},
{"learn":[0.1989022931],"iteration":903,"passed_time":0.3991247819,"remaining_time":0.04238493259},
{"learn":[0.1986047105],"iteration":904,"passed_time":0.3996716314,"remaining_time":0.04195448065},
{"learn":[0.198391087],"iteration":905,"passed_time":0.4000531553,"remaining_time":0.04150661876},
{"learn":[0.1982668728],"iteration":906,"passed_time":0.4004648445,"remaining_time":0.04106199618},
{"learn":[0.1981585715],"iteration":907,"passed_time":0.4008573262,"remaining_time":0.04061550001},
{"learn":[0.1980746601],"iteration":908,"passed_time":0.4012606824,"remaining_time":0.04017021133},
{"learn":[0.1979034336],"iteration":909,"passed_time":0.4016641219,"remaining_time":0.03972502305},
{"learn":[0.1978888492],"iteration":910,"passed_time":0.4020676031,"remaining_time":0.03927993049},
{"learn":[0.1977815829],"iteration":911,"passed_time":0.402472251,"remaining_time":0.03883504176},
{"learn":[0.1976128978],"iteration":912,"passed_time":0.402871274,"remaining_time":0.03838970519},
{"learn":[0.1975322616],"iteration":913,"passed_time":0.4033430021,"remaining_time":0.03795131092},
{"learn":[0.1973526266],"iteration":914,"passed_time":0.4037503581,"remaining_time":0.03750686387},
{"learn":[0.1971406678],"iteration":915,"passed_time":0.4041521727,"remaining_time":0.03706198964},
{"learn":[0.1969521486],"iteration":916,"passed_time":0.4045323633,"remaining_time":0.03661525208},
{"learn":[0.1966932011],"iteration":917,"passed_time":0.404926095,"remaining_time":0.03616986905},
{"learn":[0.196522913],"iteration":918,"passed_time":0.4054153639,"remaining_time":0.03573301901},
{"learn":[0.196456608],"iteration":919,"passed_time":0.4058545934,"remaining_time":0.03529170377},
{"learn":[0.1963581312],"iteration":920,"passed_time":0.4063121971,"remaining_time":0.03485196913},
{"learn":[0.1962056114],"iteration":921,"passed_time":0.4066897212,"remaining_time":0.0344054211},
{"learn":[0.1960122735],"iteration":922,"passed_time":0.4071251175,"remaining_time":0.03396385054},
{"learn":[0.1958592976],"iteration":923,"passed_time":0.4075116412,"remaining_time":0.03351827352},
{"learn":[0.1957677517],"iteration":924,"passed_time":0.4079898273,"remaining_time":0.03308025626},
{"learn":[0.1956752964],"iteration":925,"passed_time":0.4083907669,"remaining_time":0.03263597921},
{"learn":[0.1955027579],"iteration":926,"passed_time":0.4087871651,"remaining_time":0.03219143803},
{"learn":[0.1954638643],"iteration":927,"passed_time":0.4092133536,"remaining_time":0.03174931192},
{"learn":[0.1954562554],"iteration":928,"passed_time":0.4096495833,"remaining_time":0.03130798753},
{"learn":[0.1953910761],"iteration":929,"passed_time":0.4101014789,"remaining_time":0.03086785325},
{"learn":[0.1952034858],"iteration":930,"passed_time":0.4106516616,"remaining_time":0.03043497814},
{"learn":[0.1950577083],"iteration":931,"passed_time":0.4111120568,"remaining_time":0.02999530028},
{"learn":[0.1948721747],"iteration":932,"passed_time":0.4115539946,"remaining_time":0.02955425256},
{"learn":[0.1948142768],"iteration":933,"passed_time":0.4119721834,"remaining_time":0.02911152474},
{"learn":[0.1946773548],"iteration":934,"passed_time":0.4123965386,"remaining_time":0.02866927809},
{"learn":[0.1945462539],"iteration":935,"passed_time":0.4127884371,"remaining_time":0.0282248504},
{"learn":[0.1943476927],"iteration":936,"passed_time":0.4132415409,"remaining_time":0.02778465003},
{"learn":[0.1941979688],"iteration":937,"passed_time":0.4136586882,"remaining_time":0.02734204549},
{"learn":[0.1941429827],"iteration":938,"passed_time":0.4140690441,"remaining_time":0.02689905398},
{"learn":[0.1939615241],"iteration":939,"passed_time":0.4144889828,"remaining_time":0.02645674358},
{"learn":[0.19384923],"iteration":940,"passed_time":0.4149175462,"remaining_time":0.02601502149},
{"learn":[0.1937368355],"iteration":941,"passed_time":0.4153571924,"remaining_time":0.02557400972},
{"learn":[0.1935902333],"iteration":942,"passed_time":0.4157836309,"remaining_time":0.0251322025},
{"learn":[0.1934688438],"iteration":943,"passed_time":0.416188737,"remaining_time":0.02468916236},
{"learn":[0.1933233355],"iteration":944,"passed_time":0.4166004678,"remaining_time":0.02424658807},
{"learn":[0.1931741683],"iteration":945,"passed_time":0.4169951161,"remaining_time":0.02380310388},
{"learn":[0.1931327032],"iteration":946,"passed_time":0.4174955511,"remaining_time":0.0233656433},
{"learn":[0.1931209754],"iteration":947,"passed_time":0.4179249894,"remaining_time":0.02292415554},
{"learn":[0.1930794479],"iteration":948,"passed_time":0.4183495113,"remaining_time":0.02248242895},
{"learn":[0.1929338003],"iteration":949,"passed_time":0.4188035318,"remaining_time":0.02204229115},
{"learn":[0.1928282175],"iteration":950,"passed_time":0.4192164293,"remaining_time":0.02160000529},
{"learn":[0.1927001915],"iteration":951,"passed_time":0.4196631168,"remaining_time":0.02115948488},
{"learn":[0.1924770939],"iteration":952,"passed_time":0.4200965133,"remaining_time":0.02071829604},
{"learn":[0.1923998324],"iteration":953,"passed_time":0.4205144521,"remaining_time":0.0202763782},
{"learn":[0.1922718553],"iteration":954,"passed_time":0.4209633479,"remaining_time":0.01983596927},
{"learn":[0.1922294328],"iteration":955,"passed_time":0.4214741574,"remaining_time":0.01939839218},
{"learn":[0.1921740481],"iteration":956,"passed_time":0.4219833837,"remaining_time":0.01896059091},
{"learn":[0.1921151888],"iteration":957,"passed_time":0.4224088639,"remaining_time":0.01851896898},
{"learn":[0.1920821241],"iteration":958,"passed_time":0.422792846,"remaining_time":0.01807560655},
{"learn":[0.1918635497],"iteration":959,"passed_time":0.4231849111,"remaining_time":0.01763270463},
{"learn":[0.1917743735],"iteration":960,"passed_time":0.423630057,"remaining_time":0.01719206267},
{"learn":[0.1915352631],"iteration":961,"passed_time":0.4240540372,"remaining_time":0.01675057528},
{"learn":[0.1913072856],"iteration":962,"passed_time":0.4244846422,"remaining_time":0.01630937878},
{"learn":[0.1912183686],"iteration":963,"passed_time":0.4248909149,"remaining_time":0.01586729558},
{"learn":[0.1911464786],"iteration":964,"passed_time":0.4253157285,"remaining_time":0.01542595906},
{"learn":[0.1909622336],"iteration":965,"passed_time":0.4257709989,"remaining_time":0.01498572874},
{"learn":[0.1907326955],"iteration":966,"passed_time":0.4261648139,"remaining_time":0.01454337007},
{"learn":[0.1906062696],"iteration":967,"passed_time":0.426578128,"remaining_time":0.0141017563},
{"learn":[0.1904113378],"iteration":968,"passed_time":0.4270024416,"remaining_time":0.01366055283},
{"learn":[0.1902833668],"iteration":969,"passed_time":0.4274167139,"remaining_time":0.01321907363},
{"learn":[0.1901261515],"iteration":970,"passed_time":0.4278449023,"remaining_time":0.01277806608},
{"learn":[0.1899574032],"iteration":971,"passed_time":0.4282473002,"remaining_time":0.01233634198},
{"learn":[0.1899253414],"iteration":972,"passed_time":0.428652198,"remaining_time":0.01189476809},
{"learn":[0.1898868304],"iteration":973,"passed_time":0.429075595,"remaining_time":0.01145376332},
{"learn":[0.1896386182],"iteration":974,"passed_time":0.4295055333,"remaining_time":0.01101296239},
{"learn":[0.1895419709],"iteration":975,"passed_time":0.4298914736,"remaining_time":0.01057110181},
{"learn":[0.1894325585],"iteration":976,"passed_time":0.4303227452,"remaining_time":0.01013042287},
{"learn":[0.1892072325],"iteration":977,"passed_time":0.4306985194,"remaining_time":0.009688514751},
{"learn":[0.1890233516],"iteration":978,"passed_time":0.4311862883,"remaining_time":0.009249144081},
{"learn":[0.1888348736],"iteration":979,"passed_time":0.4316015606,"remaining_time":0.008808195115},
{"learn":[0.1888182459],"iteration":980,"passed_time":0.4320197912,"remaining_time":0.008367355792},
{"learn":[0.1887296289],"iteration":981,"passed_time":0.4324837279,"remaining_time":0.007927400307},
{"learn":[0.1885193937],"iteration":982,"passed_time":0.432882251,"remaining_time":0.007486264768},
{"learn":[0.1882928443],"iteration":983,"passed_time":0.4333152308,"remaining_time":0.007045776111},
{"learn":[0.1881888711],"iteration":984,"passed_time":0.4336975047,"remaining_time":0.006604530528},
{"learn":[0.1879989444],"iteration":985,"passed_time":0.4340923613,"remaining_time":0.006163583223},
{"learn":[0.1877877817],"iteration":986,"passed_time":0.4345870466,"remaining_time":0.00572404418},
{"learn":[0.187582372],"iteration":987,"passed_time":0.4350165266,"remaining_time":0.005283601537},
{"learn":[0.1874806413],"iteration":988,"passed_time":0.4354144247,"remaining_time":0.004842829799},
{"learn":[0.1873418604],"iteration":989,"passed_time":0.4358147394,"remaining_time":0.004402169085},
{"learn":[0.187264596],"iteration":990,"passed_time":0.4362151374,"remaining_time":0.003961590551},
{"learn":[0.1872234064],"iteration":991,"passed_time":0.4366425758,"remaining_time":0.003521311095},
{"learn":[0.1871830953],"iteration":992,"passed_time":0.4370915132,"remaining_time":0.003081209056},
{"learn":[0.1869594288],"iteration":993,"passed_time":0.4376245717,"remaining_time":0.002641597012},
{"learn":[0.1868407747],"iteration":994,"passed_time":0.4380264697,"remaining_time":0.002201138039},
{"learn":[0.1866216168],"iteration":995,"passed_time":0.4384317841,"remaining_time":0.001760770217},
{"learn":[0.1864796215],"iteration":996,"passed_time":0.438857181,"remaining_time":0.001320533142},
{"learn":[0.1863640673],"iteration":997,"passed_time":0.4392668702,"remaining_time":0.0008802943291},
{"learn":[0.1862683928],"iteration":998,"passed_time":0.43970135,"remaining_time":0.0004401414915},
{"learn":[0.1860938487],"iteration":999,"passed_time":0.4401344131,"remaining_time":0}
]}